{
"meta":{"test_sets":[],"test_metrics":[],"learn_metrics":[{"best_value":"Min","name":"RMSE"}],"launch_mode":"Train","parameters":"","iteration_count":1000,"learn_sets":["learn"],"name":"experiment"},
"iterations":[
{"learn":[14.59871775],"iteration":0,"passed_time":0.1417304183,"remaining_time":141.5886879},
{"learn":[14.22518863],"iteration":1,"passed_time":0.1433082679,"remaining_time":71.51082568},
{"learn":[13.8866124],"iteration":2,"passed_time":0.1479342365,"remaining_time":49.16347795},
{"learn":[13.52356875],"iteration":3,"passed_time":0.1528517809,"remaining_time":38.06009345},
{"learn":[13.18870211],"iteration":4,"passed_time":0.1535724374,"remaining_time":30.56091505},
{"learn":[12.9124226],"iteration":5,"passed_time":0.1557540063,"remaining_time":25.80324705},
{"learn":[12.60003351],"iteration":6,"passed_time":0.1598892392,"remaining_time":22.68143065},
{"learn":[12.32990573],"iteration":7,"passed_time":0.1630526087,"remaining_time":20.21852348},
{"learn":[12.0660619],"iteration":8,"passed_time":0.1660685173,"remaining_time":18.28598896},
{"learn":[11.77309809],"iteration":9,"passed_time":0.1683732185,"remaining_time":16.66894863},
{"learn":[11.49227636],"iteration":10,"passed_time":0.1698069603,"remaining_time":15.26718943},
{"learn":[11.26264833],"iteration":11,"passed_time":0.1719494263,"remaining_time":14.15716944},
{"learn":[11.04260393],"iteration":12,"passed_time":0.1742608687,"remaining_time":13.23042134},
{"learn":[10.79916926],"iteration":13,"passed_time":0.1755120401,"remaining_time":12.36106225},
{"learn":[10.5541002],"iteration":14,"passed_time":0.1763330589,"remaining_time":11.5792042},
{"learn":[10.31918115],"iteration":15,"passed_time":0.1777259527,"remaining_time":10.93014609},
{"learn":[10.10004441],"iteration":16,"passed_time":0.1790909794,"remaining_time":10.35567251},
{"learn":[9.894556723],"iteration":17,"passed_time":0.1805373508,"remaining_time":9.84931547},
{"learn":[9.690174082],"iteration":18,"passed_time":0.1821425691,"remaining_time":9.404308438},
{"learn":[9.506034866],"iteration":19,"passed_time":0.1834719009,"remaining_time":8.990123143},
{"learn":[9.338524633],"iteration":20,"passed_time":0.1848201948,"remaining_time":8.616141463},
{"learn":[9.170203312],"iteration":21,"passed_time":0.1864755797,"remaining_time":8.289687133},
{"learn":[9.010299969],"iteration":22,"passed_time":0.1877838626,"remaining_time":7.976731902},
{"learn":[8.843866678],"iteration":23,"passed_time":0.1887807875,"remaining_time":7.67708536},
{"learn":[8.690548059],"iteration":24,"passed_time":0.1898841528,"remaining_time":7.405481961},
{"learn":[8.555307687],"iteration":25,"passed_time":0.1908104632,"remaining_time":7.148053507},
{"learn":[8.413851302],"iteration":26,"passed_time":0.191802176,"remaining_time":6.911982119},
{"learn":[8.29256019],"iteration":27,"passed_time":0.1927621478,"remaining_time":6.691600272},
{"learn":[8.162193833],"iteration":28,"passed_time":0.1937600259,"remaining_time":6.487620178},
{"learn":[8.040736294],"iteration":29,"passed_time":0.1946930494,"remaining_time":6.295075265},
{"learn":[7.921220278],"iteration":30,"passed_time":0.1958327638,"remaining_time":6.121353166},
{"learn":[7.809589039],"iteration":31,"passed_time":0.1967521205,"remaining_time":5.951751644},
{"learn":[7.699675801],"iteration":32,"passed_time":0.1976288798,"remaining_time":5.791125054},
{"learn":[7.60645267],"iteration":33,"passed_time":0.1984576738,"remaining_time":5.638532732},
{"learn":[7.498880302],"iteration":34,"passed_time":0.1993319784,"remaining_time":5.495867405},
{"learn":[7.401158744],"iteration":35,"passed_time":0.200390013,"remaining_time":5.365999236},
{"learn":[7.306431077],"iteration":36,"passed_time":0.2011941446,"remaining_time":5.236485438},
{"learn":[7.223863468],"iteration":37,"passed_time":0.2019662238,"remaining_time":5.112934403},
{"learn":[7.143477682],"iteration":38,"passed_time":0.202678658,"remaining_time":4.994210008},
{"learn":[7.062817131],"iteration":39,"passed_time":0.2034442678,"remaining_time":4.882662426},
{"learn":[6.990793435],"iteration":40,"passed_time":0.2042835546,"remaining_time":4.778242168},
{"learn":[6.931862224],"iteration":41,"passed_time":0.2051506481,"remaining_time":4.679388593},
{"learn":[6.858296558],"iteration":42,"passed_time":0.2055903396,"remaining_time":4.57558035},
{"learn":[6.786268161],"iteration":43,"passed_time":0.2060632583,"remaining_time":4.477192612},
{"learn":[6.717118549],"iteration":44,"passed_time":0.2067678786,"remaining_time":4.388073869},
{"learn":[6.652948106],"iteration":45,"passed_time":0.2074657952,"remaining_time":4.302660187},
{"learn":[6.589686076],"iteration":46,"passed_time":0.2081015869,"remaining_time":4.219591751},
{"learn":[6.531283097],"iteration":47,"passed_time":0.20882563,"remaining_time":4.141708328},
{"learn":[6.471368031],"iteration":48,"passed_time":0.2095499832,"remaining_time":4.066980286},
{"learn":[6.416481395],"iteration":49,"passed_time":0.2101224231,"remaining_time":3.992326039},
{"learn":[6.369870822],"iteration":50,"passed_time":0.2107807145,"remaining_time":3.922174471},
{"learn":[6.325678067],"iteration":51,"passed_time":0.2113558765,"remaining_time":3.85318021},
{"learn":[6.275766122],"iteration":52,"passed_time":0.2119412807,"remaining_time":3.786950809},
{"learn":[6.224773967],"iteration":53,"passed_time":0.2127261094,"remaining_time":3.726646287},
{"learn":[6.182249254],"iteration":54,"passed_time":0.2133920187,"remaining_time":3.666462866},
{"learn":[6.139904173],"iteration":55,"passed_time":0.2141798895,"remaining_time":3.610460994},
{"learn":[6.100525536],"iteration":56,"passed_time":0.2147991026,"remaining_time":3.553606206},
{"learn":[6.062568564],"iteration":57,"passed_time":0.2154233594,"remaining_time":3.498772493},
{"learn":[6.030559288],"iteration":58,"passed_time":0.2161407832,"remaining_time":3.447262322},
{"learn":[5.997931376],"iteration":59,"passed_time":0.2168116337,"remaining_time":3.396715595},
{"learn":[5.964103835],"iteration":60,"passed_time":0.2173669274,"remaining_time":3.346025325},
{"learn":[5.933729724],"iteration":61,"passed_time":0.2178997775,"remaining_time":3.296612763},
{"learn":[5.901932711],"iteration":62,"passed_time":0.2185006646,"remaining_time":3.249763853},
{"learn":[5.873727795],"iteration":63,"passed_time":0.2191069568,"remaining_time":3.204439243},
{"learn":[5.846485734],"iteration":64,"passed_time":0.2196288154,"remaining_time":3.159276037},
{"learn":[5.820630862],"iteration":65,"passed_time":0.2201271601,"remaining_time":3.115132841},
{"learn":[5.793646238],"iteration":66,"passed_time":0.2206073219,"remaining_time":3.072039273},
{"learn":[5.765388646],"iteration":67,"passed_time":0.2210702873,"remaining_time":3.02996335},
{"learn":[5.747073912],"iteration":68,"passed_time":0.2216469139,"remaining_time":2.9906272},
{"learn":[5.722315217],"iteration":69,"passed_time":0.2221071205,"remaining_time":2.950851744},
{"learn":[5.699970599],"iteration":70,"passed_time":0.2225654668,"remaining_time":2.912159418},
{"learn":[5.682732647],"iteration":71,"passed_time":0.2230647146,"remaining_time":2.875056322},
{"learn":[5.663525791],"iteration":72,"passed_time":0.2235837333,"remaining_time":2.839207134},
{"learn":[5.642381613],"iteration":73,"passed_time":0.2240597766,"remaining_time":2.803775042},
{"learn":[5.621404779],"iteration":74,"passed_time":0.2245159996,"remaining_time":2.769030661},
{"learn":[5.602460129],"iteration":75,"passed_time":0.2249665694,"remaining_time":2.73511987},
{"learn":[5.587337574],"iteration":76,"passed_time":0.2254170712,"remaining_time":2.70207736},
{"learn":[5.572393026],"iteration":77,"passed_time":0.2258385418,"remaining_time":2.669527378},
{"learn":[5.558425806],"iteration":78,"passed_time":0.2263213542,"remaining_time":2.638505914},
{"learn":[5.541518902],"iteration":79,"passed_time":0.2267910808,"remaining_time":2.60809743},
{"learn":[5.526157283],"iteration":80,"passed_time":0.2273166091,"remaining_time":2.579061281},
{"learn":[5.511746977],"iteration":81,"passed_time":0.2277788056,"remaining_time":2.550011506},
{"learn":[5.504975022],"iteration":82,"passed_time":0.2280119871,"remaining_time":2.519120387},
{"learn":[5.493980522],"iteration":83,"passed_time":0.2286008938,"remaining_time":2.492838318},
{"learn":[5.480745463],"iteration":84,"passed_time":0.2290256017,"remaining_time":2.465393242},
{"learn":[5.464052013],"iteration":85,"passed_time":0.2295085644,"remaining_time":2.439195672},
{"learn":[5.449143727],"iteration":86,"passed_time":0.2299572365,"remaining_time":2.41322939},
{"learn":[5.438255432],"iteration":87,"passed_time":0.2304286499,"remaining_time":2.388078736},
{"learn":[5.425927931],"iteration":88,"passed_time":0.2308946259,"remaining_time":2.363427013},
{"learn":[5.412331217],"iteration":89,"passed_time":0.2313798093,"remaining_time":2.339506961},
{"learn":[5.400691499],"iteration":90,"passed_time":0.2317544936,"remaining_time":2.314998183},
{"learn":[5.391618744],"iteration":91,"passed_time":0.2321668073,"remaining_time":2.291385446},
{"learn":[5.380766572],"iteration":92,"passed_time":0.232566929,"remaining_time":2.268152738},
{"learn":[5.372207183],"iteration":93,"passed_time":0.2329655074,"remaining_time":2.245390954},
{"learn":[5.362918837],"iteration":94,"passed_time":0.2334284295,"remaining_time":2.223712934},
{"learn":[5.348292324],"iteration":95,"passed_time":0.2338507698,"remaining_time":2.202094749},
{"learn":[5.339772295],"iteration":96,"passed_time":0.2342741408,"remaining_time":2.180923187},
{"learn":[5.331515983],"iteration":97,"passed_time":0.2347116131,"remaining_time":2.160304847},
{"learn":[5.323861644],"iteration":98,"passed_time":0.2351376421,"remaining_time":2.139990056},
{"learn":[5.313277281],"iteration":99,"passed_time":0.2355759412,"remaining_time":2.120183471},
{"learn":[5.30685627],"iteration":100,"passed_time":0.2360477464,"remaining_time":2.101058654},
{"learn":[5.29652059],"iteration":101,"passed_time":0.2364683512,"remaining_time":2.081848818},
{"learn":[5.288350766],"iteration":102,"passed_time":0.236899776,"remaining_time":2.063098049},
{"learn":[5.27993346],"iteration":103,"passed_time":0.2373063765,"remaining_time":2.044485705},
{"learn":[5.271789139],"iteration":104,"passed_time":0.2377336978,"remaining_time":2.026396757},
{"learn":[5.262684686],"iteration":105,"passed_time":0.2381976325,"remaining_time":2.008949844},
{"learn":[5.251619772],"iteration":106,"passed_time":0.2387055672,"remaining_time":1.992187584},
{"learn":[5.241012171],"iteration":107,"passed_time":0.2391357968,"remaining_time":1.975084544},
{"learn":[5.232684032],"iteration":108,"passed_time":0.2395334133,"remaining_time":1.958020837},
{"learn":[5.224267141],"iteration":109,"passed_time":0.2399528587,"remaining_time":1.941436765},
{"learn":[5.216324968],"iteration":110,"passed_time":0.2403745361,"remaining_time":1.925161826},
{"learn":[5.211102527],"iteration":111,"passed_time":0.2407905986,"remaining_time":1.90912546},
{"learn":[5.206364257],"iteration":112,"passed_time":0.2413054774,"remaining_time":1.894141225},
{"learn":[5.196937641],"iteration":113,"passed_time":0.2417246624,"remaining_time":1.878667113},
{"learn":[5.190746047],"iteration":114,"passed_time":0.2421402262,"remaining_time":1.863426958},
{"learn":[5.181885213],"iteration":115,"passed_time":0.2425325087,"remaining_time":1.84826498},
{"learn":[5.178293568],"iteration":116,"passed_time":0.2428540801,"remaining_time":1.832821819},
{"learn":[5.170991438],"iteration":117,"passed_time":0.2432900787,"remaining_time":1.818490249},
{"learn":[5.166257212],"iteration":118,"passed_time":0.2438473896,"remaining_time":1.805290338},
{"learn":[5.161421246],"iteration":119,"passed_time":0.2442602633,"remaining_time":1.791241931},
{"learn":[5.158223542],"iteration":120,"passed_time":0.2446953463,"remaining_time":1.777580243},
{"learn":[5.15470988],"iteration":121,"passed_time":0.2450332984,"remaining_time":1.763436361},
{"learn":[5.146388143],"iteration":122,"passed_time":0.2454669697,"remaining_time":1.75019945},
{"learn":[5.139529364],"iteration":123,"passed_time":0.2459249452,"remaining_time":1.737340742},
{"learn":[5.134276023],"iteration":124,"passed_time":0.2463501731,"remaining_time":1.724451212},
{"learn":[5.128536065],"iteration":125,"passed_time":0.2467461242,"remaining_time":1.711556449},
{"learn":[5.123300353],"iteration":126,"passed_time":0.2470712622,"remaining_time":1.698371747},
{"learn":[5.116200518],"iteration":127,"passed_time":0.2475023629,"remaining_time":1.686109847},
{"learn":[5.108728704],"iteration":128,"passed_time":0.2478947502,"remaining_time":1.67376998},
{"learn":[5.104075866],"iteration":129,"passed_time":0.2483048735,"remaining_time":1.661732615},
{"learn":[5.100317606],"iteration":130,"passed_time":0.248780859,"remaining_time":1.650309668},
{"learn":[5.095814182],"iteration":131,"passed_time":0.2492409388,"remaining_time":1.638947992},
{"learn":[5.092146915],"iteration":132,"passed_time":0.2496677601,"remaining_time":1.627533444},
{"learn":[5.085258329],"iteration":133,"passed_time":0.2500859005,"remaining_time":1.61622679},
{"learn":[5.079219421],"iteration":134,"passed_time":0.2506039409,"remaining_time":1.605721547},
{"learn":[5.076476829],"iteration":135,"passed_time":0.2510115654,"remaining_time":1.59466171},
{"learn":[5.072133867],"iteration":136,"passed_time":0.2514589052,"remaining_time":1.584007556},
{"learn":[5.067031564],"iteration":137,"passed_time":0.2519056222,"remaining_time":1.573497437},
{"learn":[5.061358312],"iteration":138,"passed_time":0.2523214056,"remaining_time":1.562940505},
{"learn":[5.056759124],"iteration":139,"passed_time":0.2527057601,"remaining_time":1.552335383},
{"learn":[5.050254],"iteration":140,"passed_time":0.2531186038,"remaining_time":1.542048799},
{"learn":[5.048376474],"iteration":141,"passed_time":0.2534010183,"remaining_time":1.531113195},
{"learn":[5.042603751],"iteration":142,"passed_time":0.2540359196,"remaining_time":1.522439042},
{"learn":[5.037477349],"iteration":143,"passed_time":0.254462098,"remaining_time":1.512635805},
{"learn":[5.03230489],"iteration":144,"passed_time":0.2549162564,"remaining_time":1.503126891},
{"learn":[5.025976187],"iteration":145,"passed_time":0.2553256091,"remaining_time":1.493479932},
{"learn":[5.01952451],"iteration":146,"passed_time":0.255820702,"remaining_time":1.484456182},
{"learn":[5.017569424],"iteration":147,"passed_time":0.2562326872,"remaining_time":1.475069254},
{"learn":[5.008962367],"iteration":148,"passed_time":0.256658054,"remaining_time":1.465879221},
{"learn":[5.003880266],"iteration":149,"passed_time":0.2571102192,"remaining_time":1.456957909},
{"learn":[4.996387564],"iteration":150,"passed_time":0.2575302854,"remaining_time":1.447968293},
{"learn":[4.993361683],"iteration":151,"passed_time":0.257957132,"remaining_time":1.439129263},
{"learn":[4.99005752],"iteration":152,"passed_time":0.2584364995,"remaining_time":1.430690948},
{"learn":[4.986908764],"iteration":153,"passed_time":0.2589472047,"remaining_time":1.422528151},
{"learn":[4.985207175],"iteration":154,"passed_time":0.2593677468,"remaining_time":1.413972555},
{"learn":[4.979003494],"iteration":155,"passed_time":0.2598192031,"remaining_time":1.405688509},
{"learn":[4.973142217],"iteration":156,"passed_time":0.2602408091,"remaining_time":1.397343962},
{"learn":[4.967056696],"iteration":157,"passed_time":0.260665714,"remaining_time":1.389117286},
{"learn":[4.961460696],"iteration":158,"passed_time":0.2611446486,"remaining_time":1.381274525},
{"learn":[4.954240363],"iteration":159,"passed_time":0.2615612831,"remaining_time":1.373196736},
{"learn":[4.952320707],"iteration":160,"passed_time":0.2618051541,"remaining_time":1.364313815},
{"learn":[4.948337777],"iteration":161,"passed_time":0.2622216283,"remaining_time":1.356430398},
{"learn":[4.943228639],"iteration":162,"passed_time":0.2626266742,"remaining_time":1.348579916},
{"learn":[4.938545759],"iteration":163,"passed_time":0.2630737957,"remaining_time":1.341034715},
{"learn":[4.935330572],"iteration":164,"passed_time":0.2635744062,"remaining_time":1.333846238},
{"learn":[4.932051543],"iteration":165,"passed_time":0.2640840952,"remaining_time":1.326783948},
{"learn":[4.928964153],"iteration":166,"passed_time":0.264490111,"remaining_time":1.319283009},
{"learn":[4.922860227],"iteration":167,"passed_time":0.2649117838,"remaining_time":1.311944072},
{"learn":[4.917668772],"iteration":168,"passed_time":0.2653364837,"remaining_time":1.304701882},
{"learn":[4.910365386],"iteration":169,"passed_time":0.2657924878,"remaining_time":1.297692734},
{"learn":[4.906457206],"iteration":170,"passed_time":0.2662147046,"remaining_time":1.290596433},
{"learn":[4.901996508],"iteration":171,"passed_time":0.2666669706,"remaining_time":1.283722393},
{"learn":[4.896816173],"iteration":172,"passed_time":0.2670844468,"remaining_time":1.276756286},
{"learn":[4.891123132],"iteration":173,"passed_time":0.2674898325,"remaining_time":1.269808055},
{"learn":[4.887630202],"iteration":174,"passed_time":0.2679085909,"remaining_time":1.262997643},
{"learn":[4.885259712],"iteration":175,"passed_time":0.2684474473,"remaining_time":1.256822139},
{"learn":[4.880659728],"iteration":176,"passed_time":0.2691061174,"remaining_time":1.251267427},
{"learn":[4.877299723],"iteration":177,"passed_time":0.2695834326,"remaining_time":1.244930234},
{"learn":[4.874038772],"iteration":178,"passed_time":0.2700259123,"remaining_time":1.238498737},
{"learn":[4.86943698],"iteration":179,"passed_time":0.270415956,"remaining_time":1.23189491},
{"learn":[4.861268711],"iteration":180,"passed_time":0.2708512533,"remaining_time":1.225564511},
{"learn":[4.858673056],"iteration":181,"passed_time":0.2712409965,"remaining_time":1.219094149},
{"learn":[4.854036207],"iteration":182,"passed_time":0.2717182483,"remaining_time":1.213080923},
{"learn":[4.85130244],"iteration":183,"passed_time":0.2721891277,"remaining_time":1.20709961},
{"learn":[4.847510084],"iteration":184,"passed_time":0.2725975485,"remaining_time":1.200902714},
{"learn":[4.845691673],"iteration":185,"passed_time":0.2729758461,"remaining_time":1.19463623},
{"learn":[4.842058646],"iteration":186,"passed_time":0.2736406563,"remaining_time":1.189678361},
{"learn":[4.838623675],"iteration":187,"passed_time":0.2740903758,"remaining_time":1.183837155},
{"learn":[4.834602161],"iteration":188,"passed_time":0.2745400618,"remaining_time":1.178052858},
{"learn":[4.830858976],"iteration":189,"passed_time":0.274919643,"remaining_time":1.172025847},
{"learn":[4.827590511],"iteration":190,"passed_time":0.2753580429,"remaining_time":1.166307103},
{"learn":[4.822246226],"iteration":191,"passed_time":0.2757830993,"remaining_time":1.16058721},
{"learn":[4.816686395],"iteration":192,"passed_time":0.2762060691,"remaining_time":1.15491346},
{"learn":[4.814797121],"iteration":193,"passed_time":0.2766290862,"remaining_time":1.149294039},
{"learn":[4.811639392],"iteration":194,"passed_time":0.2770591189,"remaining_time":1.143756876},
{"learn":[4.804813432],"iteration":195,"passed_time":0.2774730934,"remaining_time":1.138205954},
{"learn":[4.80251613],"iteration":196,"passed_time":0.2778734821,"remaining_time":1.132651808},
{"learn":[4.800087884],"iteration":197,"passed_time":0.2783128478,"remaining_time":1.127307596},
{"learn":[4.794773135],"iteration":198,"passed_time":0.2787551126,"remaining_time":1.122024348},
{"learn":[4.791664833],"iteration":199,"passed_time":0.2792111339,"remaining_time":1.116844536},
{"learn":[4.785989873],"iteration":200,"passed_time":0.2796453893,"remaining_time":1.111625204},
{"learn":[4.782387142],"iteration":201,"passed_time":0.2800929887,"remaining_time":1.106505965},
{"learn":[4.778623704],"iteration":202,"passed_time":0.2805364883,"remaining_time":1.101416656},
{"learn":[4.775772178],"iteration":203,"passed_time":0.2809659056,"remaining_time":1.096317945},
{"learn":[4.77023101],"iteration":204,"passed_time":0.2813853316,"remaining_time":1.091226042},
{"learn":[4.764496689],"iteration":205,"passed_time":0.2818510191,"remaining_time":1.086357812},
{"learn":[4.763138716],"iteration":206,"passed_time":0.282254449,"remaining_time":1.081293614},
{"learn":[4.758053283],"iteration":207,"passed_time":0.2827105692,"remaining_time":1.076474859},
{"learn":[4.755063788],"iteration":208,"passed_time":0.2831129831,"remaining_time":1.071494591},
{"learn":[4.752465267],"iteration":209,"passed_time":0.283590057,"remaining_time":1.066838786},
{"learn":[4.748067377],"iteration":210,"passed_time":0.2841736786,"remaining_time":1.062621007},
{"learn":[4.744163298],"iteration":211,"passed_time":0.2847002104,"remaining_time":1.058225311},
{"learn":[4.736670896],"iteration":212,"passed_time":0.2852820829,"remaining_time":1.054070419},
{"learn":[4.73349255],"iteration":213,"passed_time":0.2857137049,"remaining_time":1.049397066},
{"learn":[4.731864595],"iteration":214,"passed_time":0.286179799,"remaining_time":1.044889034},
{"learn":[4.728398311],"iteration":215,"passed_time":0.2867061693,"remaining_time":1.040637207},
{"learn":[4.723865975],"iteration":216,"passed_time":0.2871826284,"remaining_time":1.036239622},
{"learn":[4.723483365],"iteration":217,"passed_time":0.2876316637,"remaining_time":1.031779638},
{"learn":[4.72095416],"iteration":218,"passed_time":0.2880710715,"remaining_time":1.027321949},
{"learn":[4.716173382],"iteration":219,"passed_time":0.2886357042,"remaining_time":1.02334477},
{"learn":[4.710563974],"iteration":220,"passed_time":0.2891787916,"remaining_time":1.019322528},
{"learn":[4.707160263],"iteration":221,"passed_time":0.2897261603,"remaining_time":1.015346634},
{"learn":[4.70408351],"iteration":222,"passed_time":0.2902307622,"remaining_time":1.011252476},
{"learn":[4.702501831],"iteration":223,"passed_time":0.2907097892,"remaining_time":1.00710177},
{"learn":[4.700269738],"iteration":224,"passed_time":0.2912514434,"remaining_time":1.003199416},
{"learn":[4.695346302],"iteration":225,"passed_time":0.2917999011,"remaining_time":0.9993501038},
{"learn":[4.689769299],"iteration":226,"passed_time":0.2923238517,"remaining_time":0.99544642},
{"learn":[4.687919514],"iteration":227,"passed_time":0.2928125152,"remaining_time":0.9914529022},
{"learn":[4.682982074],"iteration":228,"passed_time":0.2932948136,"remaining_time":0.9874685646},
{"learn":[4.679578702],"iteration":229,"passed_time":0.2938267456,"remaining_time":0.9836808439},
{"learn":[4.675751423],"iteration":230,"passed_time":0.294347681,"remaining_time":0.9798847043},
{"learn":[4.672710726],"iteration":231,"passed_time":0.2948194062,"remaining_time":0.9759538963},
{"learn":[4.6690533],"iteration":232,"passed_time":0.2953240191,"remaining_time":0.9721610413},
{"learn":[4.667595702],"iteration":233,"passed_time":0.2957704477,"remaining_time":0.9682058245},
{"learn":[4.664241291],"iteration":234,"passed_time":0.2962314227,"remaining_time":0.9643278227},
{"learn":[4.662246999],"iteration":235,"passed_time":0.2966858834,"remaining_time":0.9604576904},
{"learn":[4.658668443],"iteration":236,"passed_time":0.2971549152,"remaining_time":0.9566632923},
{"learn":[4.658017572],"iteration":237,"passed_time":0.2976316793,"remaining_time":0.9529215952},
{"learn":[4.657656705],"iteration":238,"passed_time":0.2981397226,"remaining_time":0.9493068153},
{"learn":[4.653242871],"iteration":239,"passed_time":0.2987096684,"remaining_time":0.9459139498},
{"learn":[4.6507302],"iteration":240,"passed_time":0.2993155234,"remaining_time":0.9426576026},
{"learn":[4.647671336],"iteration":241,"passed_time":0.2997624193,"remaining_time":0.9389252636},
{"learn":[4.645506007],"iteration":242,"passed_time":0.3001986664,"remaining_time":0.9351867921},
{"learn":[4.641297906],"iteration":243,"passed_time":0.3007071475,"remaining_time":0.9316991948},
{"learn":[4.63798107],"iteration":244,"passed_time":0.3012272469,"remaining_time":0.92827172},
{"learn":[4.635062318],"iteration":245,"passed_time":0.3017271325,"remaining_time":0.9248059265},
{"learn":[4.631606017],"iteration":246,"passed_time":0.3022165763,"remaining_time":0.9213323156},
{"learn":[4.630215494],"iteration":247,"passed_time":0.302715996,"remaining_time":0.9179130201},
{"learn":[4.62729814],"iteration":248,"passed_time":0.3032402306,"remaining_time":0.9145920207},
{"learn":[4.624691756],"iteration":249,"passed_time":0.3037661266,"remaining_time":0.9112983798},
{"learn":[4.621840053],"iteration":250,"passed_time":0.3044072897,"remaining_time":0.9083707569},
{"learn":[4.619602091],"iteration":251,"passed_time":0.304945044,"remaining_time":0.9051543369},
{"learn":[4.613584029],"iteration":252,"passed_time":0.3054318441,"remaining_time":0.9018086465},
{"learn":[4.6119388],"iteration":253,"passed_time":0.3058638673,"remaining_time":0.8983245866},
{"learn":[4.60870702],"iteration":254,"passed_time":0.3063283974,"remaining_time":0.8949594355},
{"learn":[4.604771557],"iteration":255,"passed_time":0.3068340953,"remaining_time":0.8917365895},
{"learn":[4.604231277],"iteration":256,"passed_time":0.307301236,"remaining_time":0.8884234178},
{"learn":[4.600750354],"iteration":257,"passed_time":0.3077460847,"remaining_time":0.8850681971},
{"learn":[4.596488253],"iteration":258,"passed_time":0.3083065402,"remaining_time":0.8820662019},
{"learn":[4.59470784],"iteration":259,"passed_time":0.3088160963,"remaining_time":0.8789381203},
{"learn":[4.588818005],"iteration":260,"passed_time":0.3093119378,"remaining_time":0.8757912723},
{"learn":[4.585054174],"iteration":261,"passed_time":0.3097999762,"remaining_time":0.8726426811},
{"learn":[4.581471435],"iteration":262,"passed_time":0.3102849894,"remaining_time":0.8695058449},
{"learn":[4.577555199],"iteration":263,"passed_time":0.310765029,"remaining_time":0.8663752325},
{"learn":[4.57457145],"iteration":264,"passed_time":0.3112423165,"remaining_time":0.8632569911},
{"learn":[4.573029224],"iteration":265,"passed_time":0.3118008106,"remaining_time":0.8603826879},
{"learn":[4.571326203],"iteration":266,"passed_time":0.3123655739,"remaining_time":0.8575429425},
{"learn":[4.571019224],"iteration":267,"passed_time":0.3129647067,"remaining_time":0.8548140497},
{"learn":[4.565766631],"iteration":268,"passed_time":0.3134518727,"remaining_time":0.8517967246},
{"learn":[4.563383471],"iteration":269,"passed_time":0.3140857046,"remaining_time":0.8491946827},
{"learn":[4.558165805],"iteration":270,"passed_time":0.3146477588,"remaining_time":0.8464140817},
{"learn":[4.55629209],"iteration":271,"passed_time":0.3151200953,"remaining_time":0.843409667},
{"learn":[4.549383848],"iteration":272,"passed_time":0.3156295694,"remaining_time":0.8405226993},
{"learn":[4.546227503],"iteration":273,"passed_time":0.3160988207,"remaining_time":0.8375465104},
{"learn":[4.540620977],"iteration":274,"passed_time":0.3166414632,"remaining_time":0.8347820392},
{"learn":[4.532898237],"iteration":275,"passed_time":0.3171104856,"remaining_time":0.8318405491},
{"learn":[4.529757367],"iteration":276,"passed_time":0.3176107687,"remaining_time":0.8289985046},
{"learn":[4.52579294],"iteration":277,"passed_time":0.3181294132,"remaining_time":0.8262209941},
{"learn":[4.521572155],"iteration":278,"passed_time":0.3186640242,"remaining_time":0.8235009372},
{"learn":[4.518818099],"iteration":279,"passed_time":0.3193160754,"remaining_time":0.8210984796},
{"learn":[4.514012334],"iteration":280,"passed_time":0.3198320449,"remaining_time":0.8183602857},
{"learn":[4.508331416],"iteration":281,"passed_time":0.3202953001,"remaining_time":0.8155036363},
{"learn":[4.506038537],"iteration":282,"passed_time":0.3208413057,"remaining_time":0.8128735555},
{"learn":[4.505805643],"iteration":283,"passed_time":0.3213211725,"remaining_time":0.8100914066},
{"learn":[4.501550352],"iteration":284,"passed_time":0.3217863287,"remaining_time":0.8072885088},
{"learn":[4.494692643],"iteration":285,"passed_time":0.322291504,"remaining_time":0.8046018665},
{"learn":[4.489330245],"iteration":286,"passed_time":0.3227399345,"remaining_time":0.8017894539},
{"learn":[4.484826955],"iteration":287,"passed_time":0.3231982127,"remaining_time":0.7990178036},
{"learn":[4.478285428],"iteration":288,"passed_time":0.3237107979,"remaining_time":0.7963957693},
{"learn":[4.475311671],"iteration":289,"passed_time":0.3243197655,"remaining_time":0.7940242535},
{"learn":[4.471581298],"iteration":290,"passed_time":0.3248824512,"remaining_time":0.791552089},
{"learn":[4.469164956],"iteration":291,"passed_time":0.3253815655,"remaining_time":0.7889388643},
{"learn":[4.462068024],"iteration":292,"passed_time":0.3258689103,"remaining_time":0.786311671},
{"learn":[4.458540976],"iteration":293,"passed_time":0.3263477624,"remaining_time":0.7836786404},
{"learn":[4.455757458],"iteration":294,"passed_time":0.3268346247,"remaining_time":0.7810793572},
{"learn":[4.453027414],"iteration":295,"passed_time":0.3274086282,"remaining_time":0.7787016023},
{"learn":[4.450659338],"iteration":296,"passed_time":0.3280065639,"remaining_time":0.7763926412},
{"learn":[4.444696901],"iteration":297,"passed_time":0.3285826605,"remaining_time":0.774043717},
{"learn":[4.442052813],"iteration":298,"passed_time":0.3291520683,"remaining_time":0.7716909694},
{"learn":[4.440036756],"iteration":299,"passed_time":0.3297276198,"remaining_time":0.7693644462},
{"learn":[4.435017051],"iteration":300,"passed_time":0.3303352951,"remaining_time":0.767124157},
{"learn":[4.429962125],"iteration":301,"passed_time":0.3309764225,"remaining_time":0.7649719963},
{"learn":[4.427666256],"iteration":302,"passed_time":0.3316418638,"remaining_time":0.7628857396},
{"learn":[4.425030004],"iteration":303,"passed_time":0.3322253951,"remaining_time":0.7606212992},
{"learn":[4.422588771],"iteration":304,"passed_time":0.332743797,"remaining_time":0.7582194718},
{"learn":[4.418936667],"iteration":305,"passed_time":0.3332376697,"remaining_time":0.7557743228},
{"learn":[4.416887976],"iteration":306,"passed_time":0.333799527,"remaining_time":0.7534953492},
{"learn":[4.413773354],"iteration":307,"passed_time":0.3344302082,"remaining_time":0.7513821561},
{"learn":[4.411129391],"iteration":308,"passed_time":0.3349676885,"remaining_time":0.7490701383},
{"learn":[4.40850819],"iteration":309,"passed_time":0.335450019,"remaining_time":0.7466468165},
{"learn":[4.404880292],"iteration":310,"passed_time":0.3359765795,"remaining_time":0.7443339656},
{"learn":[4.404593827],"iteration":311,"passed_time":0.33649041,"remaining_time":0.7420044939},
{"learn":[4.402139942],"iteration":312,"passed_time":0.3370416269,"remaining_time":0.7397686827},
{"learn":[4.400284725],"iteration":313,"passed_time":0.3375635005,"remaining_time":0.7374794948},
{"learn":[4.395805521],"iteration":314,"passed_time":0.3380456294,"remaining_time":0.7351150989},
{"learn":[4.392838833],"iteration":315,"passed_time":0.3385394057,"remaining_time":0.7327878275},
{"learn":[4.389213061],"iteration":316,"passed_time":0.3390824893,"remaining_time":0.7305783603},
{"learn":[4.3861981],"iteration":317,"passed_time":0.3396519933,"remaining_time":0.7284360358},
{"learn":[4.385054234],"iteration":318,"passed_time":0.3401895743,"remaining_time":0.7262354235},
{"learn":[4.379364607],"iteration":319,"passed_time":0.3407653214,"remaining_time":0.724126308},
{"learn":[4.378387619],"iteration":320,"passed_time":0.3412662283,"remaining_time":0.7218684393},
{"learn":[4.375816727],"iteration":321,"passed_time":0.3418930097,"remaining_time":0.7198865234},
{"learn":[4.374600202],"iteration":322,"passed_time":0.3424489902,"remaining_time":0.7177646018},
{"learn":[4.37098897],"iteration":323,"passed_time":0.3430833982,"remaining_time":0.7158159789},
{"learn":[4.367418484],"iteration":324,"passed_time":0.3436227491,"remaining_time":0.7136780174},
{"learn":[4.363584638],"iteration":325,"passed_time":0.3442138188,"remaining_time":0.7116567911},
{"learn":[4.360770706],"iteration":326,"passed_time":0.3447523327,"remaining_time":0.7095361466},
{"learn":[4.358675808],"iteration":327,"passed_time":0.3452536264,"remaining_time":0.7073488932},
{"learn":[4.354228195],"iteration":328,"passed_time":0.3458278136,"remaining_time":0.705320556},
{"learn":[4.353773425],"iteration":329,"passed_time":0.3465181386,"remaining_time":0.7035368268},
{"learn":[4.351648009],"iteration":330,"passed_time":0.3471082107,"remaining_time":0.7015570785},
{"learn":[4.348209927],"iteration":331,"passed_time":0.3476787092,"remaining_time":0.6995463185},
{"learn":[4.345852733],"iteration":332,"passed_time":0.3482011943,"remaining_time":0.6974480378},
{"learn":[4.34237339],"iteration":333,"passed_time":0.3488186152,"remaining_time":0.6955484961},
{"learn":[4.340814362],"iteration":334,"passed_time":0.3494104749,"remaining_time":0.6936058681},
{"learn":[4.339707068],"iteration":335,"passed_time":0.3499705376,"remaining_time":0.6916084433},
{"learn":[4.335430786],"iteration":336,"passed_time":0.3505582177,"remaining_time":0.6896738823},
{"learn":[4.33521887],"iteration":337,"passed_time":0.351106806,"remaining_time":0.6876707264},
{"learn":[4.328507238],"iteration":338,"passed_time":0.3516574928,"remaining_time":0.6856802442},
{"learn":[4.326140732],"iteration":339,"passed_time":0.3522615332,"remaining_time":0.6838017998},
{"learn":[4.323785636],"iteration":340,"passed_time":0.3528551992,"remaining_time":0.6819107809},
{"learn":[4.320632534],"iteration":341,"passed_time":0.3534136092,"remaining_time":0.679959517},
{"learn":[4.31973724],"iteration":342,"passed_time":0.3541050733,"remaining_time":0.6782712336},
{"learn":[4.318000924],"iteration":343,"passed_time":0.3545921925,"remaining_time":0.6761990647},
{"learn":[4.312713628],"iteration":344,"passed_time":0.355188412,"remaining_time":0.674343217},
{"learn":[4.308220789],"iteration":345,"passed_time":0.3557073633,"remaining_time":0.6723486},
{"learn":[4.305890947],"iteration":346,"passed_time":0.3561833952,"remaining_time":0.6702817206},
{"learn":[4.305137856],"iteration":347,"passed_time":0.3566817228,"remaining_time":0.6682657566},
{"learn":[4.304787172],"iteration":348,"passed_time":0.3572679852,"remaining_time":0.6664225168},
{"learn":[4.30350134],"iteration":349,"passed_time":0.357856449,"remaining_time":0.6645905481},
{"learn":[4.30293809],"iteration":350,"passed_time":0.3584178033,"remaining_time":0.6627155394},
{"learn":[4.299548459],"iteration":351,"passed_time":0.3590439585,"remaining_time":0.6609672872},
{"learn":[4.294768408],"iteration":352,"passed_time":0.3596415317,"remaining_time":0.6591730058},
{"learn":[4.294581479],"iteration":353,"passed_time":0.360138199,"remaining_time":0.6572013461},
{"learn":[4.292551604],"iteration":354,"passed_time":0.3606435992,"remaining_time":0.6552538633},
{"learn":[4.288628894],"iteration":355,"passed_time":0.3611848655,"remaining_time":0.6533793635},
{"learn":[4.287802767],"iteration":356,"passed_time":0.3616935909,"remaining_time":0.6514537226},
{"learn":[4.284566905],"iteration":357,"passed_time":0.3622652255,"remaining_time":0.6496488123},
{"learn":[4.27890232],"iteration":358,"passed_time":0.3627953789,"remaining_time":0.6477767072},
{"learn":[4.276938023],"iteration":359,"passed_time":0.3632909982,"remaining_time":0.6458506634},
{"learn":[4.273425094],"iteration":360,"passed_time":0.3639921027,"remaining_time":0.6442962705},
{"learn":[4.269726505],"iteration":361,"passed_time":0.3645381608,"remaining_time":0.6424733331},
{"learn":[4.265565857],"iteration":362,"passed_time":0.3650485199,"remaining_time":0.6405947856},
{"learn":[4.262117173],"iteration":363,"passed_time":0.3655941855,"remaining_time":0.638785445},
{"learn":[4.259185148],"iteration":364,"passed_time":0.3660722059,"remaining_time":0.6368653445},
{"learn":[4.257668507],"iteration":365,"passed_time":0.3665386791,"remaining_time":0.6349331217},
{"learn":[4.253432436],"iteration":366,"passed_time":0.3670840553,"remaining_time":0.6331449782},
{"learn":[4.250216667],"iteration":367,"passed_time":0.3676203911,"remaining_time":0.631348063},
{"learn":[4.24514828],"iteration":368,"passed_time":0.3681780692,"remaining_time":0.629594476},
{"learn":[4.244015772],"iteration":369,"passed_time":0.3687437993,"remaining_time":0.6278610637},
{"learn":[4.240329192],"iteration":370,"passed_time":0.3693657199,"remaining_time":0.6262292124},
{"learn":[4.236718014],"iteration":371,"passed_time":0.3698756338,"remaining_time":0.6244137043},
{"learn":[4.233495944],"iteration":372,"passed_time":0.3703659644,"remaining_time":0.6225722779},
{"learn":[4.230357491],"iteration":373,"passed_time":0.370862418,"remaining_time":0.6207483253},
{"learn":[4.227381215],"iteration":374,"passed_time":0.3714054909,"remaining_time":0.6190091516},
{"learn":[4.226169067],"iteration":375,"passed_time":0.3718859317,"remaining_time":0.6171723974},
{"learn":[4.225963861],"iteration":376,"passed_time":0.3723313885,"remaining_time":0.6152850266},
{"learn":[4.224346548],"iteration":377,"passed_time":0.3728490034,"remaining_time":0.6135240215},
{"learn":[4.222595381],"iteration":378,"passed_time":0.373368434,"remaining_time":0.6117725527},
{"learn":[4.219700938],"iteration":379,"passed_time":0.3739765391,"remaining_time":0.6101722481},
{"learn":[4.216356207],"iteration":380,"passed_time":0.3744879796,"remaining_time":0.6084201034},
{"learn":[4.214326494],"iteration":381,"passed_time":0.3749668625,"remaining_time":0.6066217827},
{"learn":[4.212901398],"iteration":382,"passed_time":0.3754708569,"remaining_time":0.604870806},
{"learn":[4.211331091],"iteration":383,"passed_time":0.3759417624,"remaining_time":0.6030732438},
{"learn":[4.208624791],"iteration":384,"passed_time":0.3764280735,"remaining_time":0.6013071824},
{"learn":[4.204659106],"iteration":385,"passed_time":0.3769417802,"remaining_time":0.5995913291},
{"learn":[4.202968852],"iteration":386,"passed_time":0.3774423387,"remaining_time":0.597860862},
{"learn":[4.197261935],"iteration":387,"passed_time":0.3779502901,"remaining_time":0.5961483957},
{"learn":[4.196934403],"iteration":388,"passed_time":0.3784359868,"remaining_time":0.594407167},
{"learn":[4.192479929],"iteration":389,"passed_time":0.379001218,"remaining_time":0.5927967769},
{"learn":[4.190243116],"iteration":390,"passed_time":0.3794971143,"remaining_time":0.5910837407},
{"learn":[4.185852431],"iteration":391,"passed_time":0.3800046285,"remaining_time":0.589394934},
{"learn":[4.180967944],"iteration":392,"passed_time":0.3805026701,"remaining_time":0.5876975083},
{"learn":[4.178283162],"iteration":393,"passed_time":0.3810436705,"remaining_time":0.5860722444},
{"learn":[4.176341157],"iteration":394,"passed_time":0.3815509697,"remaining_time":0.5844008524},
{"learn":[4.176041504],"iteration":395,"passed_time":0.3820656039,"remaining_time":0.5827465272},
{"learn":[4.175564513],"iteration":396,"passed_time":0.3825707845,"remaining_time":0.5810835846},
{"learn":[4.170830274],"iteration":397,"passed_time":0.3830774343,"remaining_time":0.579428682},
{"learn":[4.167804808],"iteration":398,"passed_time":0.3836237847,"remaining_time":0.5778393349},
{"learn":[4.165860548],"iteration":399,"passed_time":0.3842533112,"remaining_time":0.5763799668},
{"learn":[4.160950571],"iteration":400,"passed_time":0.3847936174,"remaining_time":0.5747914633},
{"learn":[4.158544115],"iteration":401,"passed_time":0.3853326826,"remaining_time":0.5732063289},
{"learn":[4.154448767],"iteration":402,"passed_time":0.3859286302,"remaining_time":0.5717106506},
{"learn":[4.15197457],"iteration":403,"passed_time":0.386449905,"remaining_time":0.5701092658},
{"learn":[4.149562679],"iteration":404,"passed_time":0.3869107091,"remaining_time":0.5684243751},
{"learn":[4.149327961],"iteration":405,"passed_time":0.3873645945,"remaining_time":0.5667353919},
{"learn":[4.147444889],"iteration":406,"passed_time":0.3878177349,"remaining_time":0.5650513926},
{"learn":[4.147254809],"iteration":407,"passed_time":0.3882719547,"remaining_time":0.5633749931},
{"learn":[4.144589165],"iteration":408,"passed_time":0.3889746926,"remaining_time":0.5620636757},
{"learn":[4.141691034],"iteration":409,"passed_time":0.389542207,"remaining_time":0.560560737},
{"learn":[4.138893468],"iteration":410,"passed_time":0.3900288717,"remaining_time":0.5589464852},
{"learn":[4.136964597],"iteration":411,"passed_time":0.3904982886,"remaining_time":0.5573130915},
{"learn":[4.133773523],"iteration":412,"passed_time":0.3910437316,"remaining_time":0.5557933908},
{"learn":[4.131363444],"iteration":413,"passed_time":0.3915672359,"remaining_time":0.5542473436},
{"learn":[4.130228592],"iteration":414,"passed_time":0.3920699681,"remaining_time":0.552676943},
{"learn":[4.12884186],"iteration":415,"passed_time":0.392553954,"remaining_time":0.5510853585},
{"learn":[4.12413494],"iteration":416,"passed_time":0.3930142848,"remaining_time":0.5494660145},
{"learn":[4.119422508],"iteration":417,"passed_time":0.3935033939,"remaining_time":0.5478922852},
{"learn":[4.117038244],"iteration":418,"passed_time":0.3941098346,"remaining_time":0.5464864294},
{"learn":[4.116067631],"iteration":419,"passed_time":0.3946258368,"remaining_time":0.5449594889},
{"learn":[4.110343455],"iteration":420,"passed_time":0.395131187,"remaining_time":0.5434227013},
{"learn":[4.105604544],"iteration":421,"passed_time":0.3956861022,"remaining_time":0.5419586897},
{"learn":[4.103390131],"iteration":422,"passed_time":0.3962268078,"remaining_time":0.5404795937},
{"learn":[4.096724402],"iteration":423,"passed_time":0.396732446,"remaining_time":0.5389572852},
{"learn":[4.093431279],"iteration":424,"passed_time":0.3972951414,"remaining_time":0.537516956},
{"learn":[4.091412744],"iteration":425,"passed_time":0.3978047572,"remaining_time":0.5360092269},
{"learn":[4.091192901],"iteration":426,"passed_time":0.3982857854,"remaining_time":0.5344678104},
{"learn":[4.088994581],"iteration":427,"passed_time":0.3988342739,"remaining_time":0.5330215062},
{"learn":[4.087845355],"iteration":428,"passed_time":0.3994619323,"remaining_time":0.5316847631},
{"learn":[4.083650279],"iteration":429,"passed_time":0.4000707477,"remaining_time":0.53032634},
{"learn":[4.079840652],"iteration":430,"passed_time":0.4005735814,"remaining_time":0.5288314798},
{"learn":[4.075707828],"iteration":431,"passed_time":0.4011019765,"remaining_time":0.527374821},
{"learn":[4.071345409],"iteration":432,"passed_time":0.4015656128,"remaining_time":0.5258376501},
{"learn":[4.067460475],"iteration":433,"passed_time":0.4020998313,"remaining_time":0.5243974759},
{"learn":[4.064914749],"iteration":434,"passed_time":0.4026201383,"remaining_time":0.522943398},
{"learn":[4.063823175],"iteration":435,"passed_time":0.4031030122,"remaining_time":0.5214451809},
{"learn":[4.058898471],"iteration":436,"passed_time":0.4036031237,"remaining_time":0.5199738184},
{"learn":[4.054120355],"iteration":437,"passed_time":0.4041552347,"remaining_time":0.5185736117},
{"learn":[4.052715901],"iteration":438,"passed_time":0.4046920999,"remaining_time":0.517157786},
{"learn":[4.052114167],"iteration":439,"passed_time":0.4051453391,"remaining_time":0.5156395225},
{"learn":[4.051377267],"iteration":440,"passed_time":0.4056558738,"remaining_time":0.5141987153},
{"learn":[4.049275336],"iteration":441,"passed_time":0.4061666601,"remaining_time":0.5127624352},
{"learn":[4.047099198],"iteration":442,"passed_time":0.4066520759,"remaining_time":0.511298434},
{"learn":[4.044348685],"iteration":443,"passed_time":0.4071996482,"remaining_time":0.5099166765},
{"learn":[4.042822379],"iteration":444,"passed_time":0.4077556451,"remaining_time":0.5085491753},
{"learn":[4.041258611],"iteration":445,"passed_time":0.4082412143,"remaining_time":0.5070978312},
{"learn":[4.040044254],"iteration":446,"passed_time":0.4088357327,"remaining_time":0.5057855933},
{"learn":[4.036860137],"iteration":447,"passed_time":0.409402648,"remaining_time":0.5044425485},
{"learn":[4.036372284],"iteration":448,"passed_time":0.4098870038,"remaining_time":0.503001646},
{"learn":[4.03368231],"iteration":449,"passed_time":0.4103629082,"remaining_time":0.5015546655},
{"learn":[4.032439519],"iteration":450,"passed_time":0.4108893616,"remaining_time":0.5001735244},
{"learn":[4.032008634],"iteration":451,"passed_time":0.4113441567,"remaining_time":0.4987092874},
{"learn":[4.030034932],"iteration":452,"passed_time":0.4119450368,"remaining_time":0.4974259054},
{"learn":[4.028173412],"iteration":453,"passed_time":0.4124619335,"remaining_time":0.496044528},
{"learn":[4.023806097],"iteration":454,"passed_time":0.4129205742,"remaining_time":0.4945971713},
{"learn":[4.020239186],"iteration":455,"passed_time":0.4133759821,"remaining_time":0.4931502945},
{"learn":[4.017384838],"iteration":456,"passed_time":0.4140647722,"remaining_time":0.4919850576},
{"learn":[4.016468229],"iteration":457,"passed_time":0.4146315937,"remaining_time":0.4906775629},
{"learn":[4.014530169],"iteration":458,"passed_time":0.4151438866,"remaining_time":0.4893090254},
{"learn":[4.012884822],"iteration":459,"passed_time":0.4156384178,"remaining_time":0.4879233601},
{"learn":[4.008924707],"iteration":460,"passed_time":0.4161056513,"remaining_time":0.4865096444},
{"learn":[4.008286778],"iteration":461,"passed_time":0.4165959699,"remaining_time":0.4851269087},
{"learn":[4.006444202],"iteration":462,"passed_time":0.4171376251,"remaining_time":0.4838075695},
{"learn":[4.003284363],"iteration":463,"passed_time":0.4177198453,"remaining_time":0.482538442},
{"learn":[3.999811484],"iteration":464,"passed_time":0.4182063972,"remaining_time":0.4811621989},
{"learn":[3.997483319],"iteration":465,"passed_time":0.418702209,"remaining_time":0.4798003854},
{"learn":[3.99708333],"iteration":466,"passed_time":0.4193331435,"remaining_time":0.4785965},
{"learn":[3.995860263],"iteration":467,"passed_time":0.4198303942,"remaining_time":0.4772430976},
{"learn":[3.994131111],"iteration":468,"passed_time":0.4203199451,"remaining_time":0.4758846287},
{"learn":[3.993125499],"iteration":469,"passed_time":0.4208304611,"remaining_time":0.4745534987},
{"learn":[3.992954084],"iteration":470,"passed_time":0.4213063962,"remaining_time":0.473187014},
{"learn":[3.990635743],"iteration":471,"passed_time":0.4218126358,"remaining_time":0.4718582028},
{"learn":[3.986678254],"iteration":472,"passed_time":0.4223764042,"remaining_time":0.4705969662},
{"learn":[3.986393291],"iteration":473,"passed_time":0.4229103523,"remaining_time":0.4693055808},
{"learn":[3.986152671],"iteration":474,"passed_time":0.4234008007,"remaining_time":0.467969306},
{"learn":[3.985596662],"iteration":475,"passed_time":0.4239059082,"remaining_time":0.4666527225},
{"learn":[3.983853457],"iteration":476,"passed_time":0.4245033002,"remaining_time":0.4654407254},
{"learn":[3.983263928],"iteration":477,"passed_time":0.4250133143,"remaining_time":0.4641358788},
{"learn":[3.980067202],"iteration":478,"passed_time":0.4254917058,"remaining_time":0.4627999556},
{"learn":[3.978115407],"iteration":479,"passed_time":0.4259856676,"remaining_time":0.4614844733},
{"learn":[3.972661644],"iteration":480,"passed_time":0.4266034012,"remaining_time":0.4603059569},
{"learn":[3.969938254],"iteration":481,"passed_time":0.42714524,"remaining_time":0.459048204},
{"learn":[3.968211434],"iteration":482,"passed_time":0.4276755212,"remaining_time":0.4577810444},
{"learn":[3.966113368],"iteration":483,"passed_time":0.4282981303,"remaining_time":0.4566153621},
{"learn":[3.962246044],"iteration":484,"passed_time":0.4289012922,"remaining_time":0.4554312691},
{"learn":[3.961319703],"iteration":485,"passed_time":0.429508016,"remaining_time":0.4542533338},
{"learn":[3.96078191],"iteration":486,"passed_time":0.4299921361,"remaining_time":0.4529485951},
{"learn":[3.958913633],"iteration":487,"passed_time":0.4304861306,"remaining_time":0.4516575797},
{"learn":[3.957428286],"iteration":488,"passed_time":0.4310648194,"remaining_time":0.4504583287},
{"learn":[3.952641965],"iteration":489,"passed_time":0.4315975941,"remaining_time":0.4492138224},
{"learn":[3.951486786],"iteration":490,"passed_time":0.432085567,"remaining_time":0.4479257711},
{"learn":[3.94938344],"iteration":491,"passed_time":0.4326261212,"remaining_time":0.4466952633},
{"learn":[3.947297924],"iteration":492,"passed_time":0.433112434,"remaining_time":0.4454117729},
{"learn":[3.946284886],"iteration":493,"passed_time":0.4336139514,"remaining_time":0.4441470838},
{"learn":[3.943288204],"iteration":494,"passed_time":0.4342045091,"remaining_time":0.4429763174},
{"learn":[3.943076488],"iteration":495,"passed_time":0.4347556813,"remaining_time":0.4417678697},
{"learn":[3.942347078],"iteration":496,"passed_time":0.4352399823,"remaining_time":0.4404943885},
{"learn":[3.940251541],"iteration":497,"passed_time":0.4357441576,"remaining_time":0.4392441107},
{"learn":[3.939011019],"iteration":498,"passed_time":0.4362557623,"remaining_time":0.4380042824},
{"learn":[3.938760512],"iteration":499,"passed_time":0.4367095275,"remaining_time":0.4367095275},
{"learn":[3.934522727],"iteration":500,"passed_time":0.4371879955,"remaining_time":0.435442734},
{"learn":[3.930091193],"iteration":501,"passed_time":0.4378051878,"remaining_time":0.4343167002},
{"learn":[3.927671752],"iteration":502,"passed_time":0.4383620618,"remaining_time":0.4331330909},
{"learn":[3.927280041],"iteration":503,"passed_time":0.4388829732,"remaining_time":0.4319165768},
{"learn":[3.925987561],"iteration":504,"passed_time":0.4394752327,"remaining_time":0.4307727529},
{"learn":[3.921645957],"iteration":505,"passed_time":0.4399689556,"remaining_time":0.4295349092},
{"learn":[3.920333743],"iteration":506,"passed_time":0.4404776887,"remaining_time":0.4283145967},
{"learn":[3.918659461],"iteration":507,"passed_time":0.4411803996,"remaining_time":0.4272849539},
{"learn":[3.916124385],"iteration":508,"passed_time":0.4417309864,"remaining_time":0.4261098513},
{"learn":[3.913849268],"iteration":509,"passed_time":0.4422739532,"remaining_time":0.4249298766},
{"learn":[3.912826119],"iteration":510,"passed_time":0.4428072519,"remaining_time":0.4237431432},
{"learn":[3.910034145],"iteration":511,"passed_time":0.4433832389,"remaining_time":0.4225996496},
{"learn":[3.90792379],"iteration":512,"passed_time":0.4440114628,"remaining_time":0.4215079578},
{"learn":[3.907823851],"iteration":513,"passed_time":0.4445780914,"remaining_time":0.4203598296},
{"learn":[3.904527401],"iteration":514,"passed_time":0.4451209568,"remaining_time":0.4191915806},
{"learn":[3.903378283],"iteration":515,"passed_time":0.4457251837,"remaining_time":0.4180833119},
{"learn":[3.902170135],"iteration":516,"passed_time":0.4462949119,"remaining_time":0.416944763},
{"learn":[3.899435429],"iteration":517,"passed_time":0.4468606167,"remaining_time":0.4158046665},
{"learn":[3.897497505],"iteration":518,"passed_time":0.4473779019,"remaining_time":0.4146219091},
{"learn":[3.896426119],"iteration":519,"passed_time":0.4479118137,"remaining_time":0.4134570588},
{"learn":[3.896044669],"iteration":520,"passed_time":0.4484814658,"remaining_time":0.4123274896},
{"learn":[3.892795942],"iteration":521,"passed_time":0.449083038,"remaining_time":0.4112292954},
{"learn":[3.892413888],"iteration":522,"passed_time":0.4497374034,"remaining_time":0.41018115},
{"learn":[3.891738985],"iteration":523,"passed_time":0.4502215709,"remaining_time":0.4089799003},
{"learn":[3.88822057],"iteration":524,"passed_time":0.4507537942,"remaining_time":0.4078248615},
{"learn":[3.883837053],"iteration":525,"passed_time":0.4512928535,"remaining_time":0.4066783509},
{"learn":[3.881769742],"iteration":526,"passed_time":0.4518246556,"remaining_time":0.4055276321},
{"learn":[3.880356898],"iteration":527,"passed_time":0.4523961257,"remaining_time":0.4044147184},
{"learn":[3.879250273],"iteration":528,"passed_time":0.4529102308,"remaining_time":0.4032527764},
{"learn":[3.877174493],"iteration":529,"passed_time":0.4534114257,"remaining_time":0.4020818304},
{"learn":[3.875854201],"iteration":530,"passed_time":0.4539737119,"remaining_time":0.4009673651},
{"learn":[3.873189396],"iteration":531,"passed_time":0.4546584929,"remaining_time":0.3999627344},
{"learn":[3.871583368],"iteration":532,"passed_time":0.4552580841,"remaining_time":0.3988846628},
{"learn":[3.869622679],"iteration":533,"passed_time":0.4558602434,"remaining_time":0.3978106244},
{"learn":[3.866860164],"iteration":534,"passed_time":0.4563975778,"remaining_time":0.3966820069},
{"learn":[3.864498444],"iteration":535,"passed_time":0.4568732346,"remaining_time":0.3955022031},
{"learn":[3.861416322],"iteration":536,"passed_time":0.4573835276,"remaining_time":0.3943548851},
{"learn":[3.860265769],"iteration":537,"passed_time":0.457869715,"remaining_time":0.3931892348},
{"learn":[3.859328725],"iteration":538,"passed_time":0.4583419361,"remaining_time":0.3920141606},
{"learn":[3.858521278],"iteration":539,"passed_time":0.4587963441,"remaining_time":0.3908265154},
{"learn":[3.85599111],"iteration":540,"passed_time":0.4593862317,"remaining_time":0.3897565256},
{"learn":[3.852379816],"iteration":541,"passed_time":0.4599763259,"remaining_time":0.388688482},
{"learn":[3.851327537],"iteration":542,"passed_time":0.4605163503,"remaining_time":0.3875800591},
{"learn":[3.847854898],"iteration":543,"passed_time":0.4610295757,"remaining_time":0.386451262},
{"learn":[3.847083414],"iteration":544,"passed_time":0.4614848709,"remaining_time":0.3852763601},
{"learn":[3.845397429],"iteration":545,"passed_time":0.462074394,"remaining_time":0.3842157049},
{"learn":[3.841933528],"iteration":546,"passed_time":0.4626395554,"remaining_time":0.3831365971},
{"learn":[3.840996474],"iteration":547,"passed_time":0.4631485802,"remaining_time":0.3820130625},
{"learn":[3.838355966],"iteration":548,"passed_time":0.4636463421,"remaining_time":0.3808825142},
{"learn":[3.83342799],"iteration":549,"passed_time":0.4643022441,"remaining_time":0.3798836543},
{"learn":[3.828161535],"iteration":550,"passed_time":0.4647995468,"remaining_time":0.3787567995},
{"learn":[3.823502399],"iteration":551,"passed_time":0.4653498896,"remaining_time":0.3776752727},
{"learn":[3.820068862],"iteration":552,"passed_time":0.4658499678,"remaining_time":0.3765550373},
{"learn":[3.817951642],"iteration":553,"passed_time":0.4663192706,"remaining_time":0.3754122648},
{"learn":[3.815785958],"iteration":554,"passed_time":0.4668331675,"remaining_time":0.3743076748},
{"learn":[3.81503012],"iteration":555,"passed_time":0.4673118394,"remaining_time":0.3731770804},
{"learn":[3.813529315],"iteration":556,"passed_time":0.4678728997,"remaining_time":0.3721143529},
{"learn":[3.808881326],"iteration":557,"passed_time":0.4684076889,"remaining_time":0.3710326138},
{"learn":[3.808740434],"iteration":558,"passed_time":0.4689870552,"remaining_time":0.3699879988},
{"learn":[3.80714352],"iteration":559,"passed_time":0.4696041006,"remaining_time":0.3689746505},
{"learn":[3.80573346],"iteration":560,"passed_time":0.4701111089,"remaining_time":0.3678766075},
{"learn":[3.803370052],"iteration":561,"passed_time":0.4705912386,"remaining_time":0.3667597198},
{"learn":[3.803215211],"iteration":562,"passed_time":0.4710966108,"remaining_time":0.3656646872},
{"learn":[3.801309667],"iteration":563,"passed_time":0.4716223022,"remaining_time":0.3645874535},
{"learn":[3.800003847],"iteration":564,"passed_time":0.472071485,"remaining_time":0.3634532672},
{"learn":[3.798026138],"iteration":565,"passed_time":0.4725315682,"remaining_time":0.3623298597},
{"learn":[3.794745847],"iteration":566,"passed_time":0.4729907248,"remaining_time":0.3612080844},
{"learn":[3.794312041],"iteration":567,"passed_time":0.4734525916,"remaining_time":0.3600907034},
{"learn":[3.792205926],"iteration":568,"passed_time":0.4740213345,"remaining_time":0.359056582},
{"learn":[3.788991061],"iteration":569,"passed_time":0.4745558214,"remaining_time":0.3579982512},
{"learn":[3.787391572],"iteration":570,"passed_time":0.4750811587,"remaining_time":0.356934881},
{"learn":[3.7826445],"iteration":571,"passed_time":0.4755612243,"remaining_time":0.3558395175},
{"learn":[3.781700331],"iteration":572,"passed_time":0.4760662594,"remaining_time":0.3547649088},
{"learn":[3.780045374],"iteration":573,"passed_time":0.4765298543,"remaining_time":0.3536615295},
{"learn":[3.775462644],"iteration":574,"passed_time":0.4770142868,"remaining_time":0.3525757772},
{"learn":[3.773711943],"iteration":575,"passed_time":0.4774941969,"remaining_time":0.3514887839},
{"learn":[3.772415806],"iteration":576,"passed_time":0.4779632194,"remaining_time":0.350395913},
{"learn":[3.770170875],"iteration":577,"passed_time":0.47842235,"remaining_time":0.3492979787},
{"learn":[3.765166479],"iteration":578,"passed_time":0.4789520855,"remaining_time":0.348253589},
{"learn":[3.763976102],"iteration":579,"passed_time":0.4795783546,"remaining_time":0.3472808774},
{"learn":[3.760761708],"iteration":580,"passed_time":0.4800940677,"remaining_time":0.3462296289},
{"learn":[3.758155662],"iteration":581,"passed_time":0.4805679336,"remaining_time":0.3451501654},
{"learn":[3.756844548],"iteration":582,"passed_time":0.4810953746,"remaining_time":0.3441110998},
{"learn":[3.753098923],"iteration":583,"passed_time":0.4815994778,"remaining_time":0.3430571623},
{"learn":[3.751618946],"iteration":584,"passed_time":0.4820933809,"remaining_time":0.3419978685},
{"learn":[3.751398464],"iteration":585,"passed_time":0.4825467603,"remaining_time":0.340911875},
{"learn":[3.749920103],"iteration":586,"passed_time":0.4830898266,"remaining_time":0.3398911386},
{"learn":[3.748237465],"iteration":587,"passed_time":0.4836425721,"remaining_time":0.338878809},
{"learn":[3.746021536],"iteration":588,"passed_time":0.4842208824,"remaining_time":0.3378858789},
{"learn":[3.74417648],"iteration":589,"passed_time":0.4846862148,"remaining_time":0.3368158442},
{"learn":[3.738788389],"iteration":590,"passed_time":0.4851792508,"remaining_time":0.3357670281},
{"learn":[3.736021611],"iteration":591,"passed_time":0.4856244506,"remaining_time":0.3346871213},
{"learn":[3.734546151],"iteration":592,"passed_time":0.486137662,"remaining_time":0.3336560344},
{"learn":[3.733527479],"iteration":593,"passed_time":0.4866705458,"remaining_time":0.3326401373},
{"learn":[3.733026392],"iteration":594,"passed_time":0.4872679311,"remaining_time":0.3316697682},
{"learn":[3.730314752],"iteration":595,"passed_time":0.4878907902,"remaining_time":0.3307179182},
{"learn":[3.727342596],"iteration":596,"passed_time":0.4884553766,"remaining_time":0.3297278338},
{"learn":[3.725459604],"iteration":597,"passed_time":0.4890612353,"remaining_time":0.3287669173},
{"learn":[3.723158842],"iteration":598,"passed_time":0.4896492261,"remaining_time":0.3277952248},
{"learn":[3.722362756],"iteration":599,"passed_time":0.4901614673,"remaining_time":0.3267743115},
{"learn":[3.721443615],"iteration":600,"passed_time":0.4906725653,"remaining_time":0.325754332},
{"learn":[3.720743486],"iteration":601,"passed_time":0.4911411652,"remaining_time":0.3247079464},
{"learn":[3.720215334],"iteration":602,"passed_time":0.491608404,"remaining_time":0.3236625811},
{"learn":[3.719436563],"iteration":603,"passed_time":0.4921460242,"remaining_time":0.3226652741},
{"learn":[3.715046574],"iteration":604,"passed_time":0.4926749006,"remaining_time":0.3216637781},
{"learn":[3.71443396],"iteration":605,"passed_time":0.4931360891,"remaining_time":0.3206198335},
{"learn":[3.712938941],"iteration":606,"passed_time":0.4936108568,"remaining_time":0.3195866009},
{"learn":[3.712814764],"iteration":607,"passed_time":0.4942140311,"remaining_time":0.3186379937},
{"learn":[3.71235348],"iteration":608,"passed_time":0.4947749142,"remaining_time":0.3176633685},
{"learn":[3.711223749],"iteration":609,"passed_time":0.4952376807,"remaining_time":0.3166273696},
{"learn":[3.710755648],"iteration":610,"passed_time":0.4957770363,"remaining_time":0.3156420084},
{"learn":[3.708668039],"iteration":611,"passed_time":0.4962648224,"remaining_time":0.3146254103},
{"learn":[3.705623591],"iteration":612,"passed_time":0.496770844,"remaining_time":0.31362205},
{"learn":[3.704045802],"iteration":613,"passed_time":0.4972743792,"remaining_time":0.3126187466},
{"learn":[3.699915209],"iteration":614,"passed_time":0.4979546983,"remaining_time":0.311727738},
{"learn":[3.696182221],"iteration":615,"passed_time":0.4987629344,"remaining_time":0.3109171539},
{"learn":[3.694263278],"iteration":616,"passed_time":0.4994229406,"remaining_time":0.3100145644},
{"learn":[3.693810229],"iteration":617,"passed_time":0.4999363329,"remaining_time":0.3090221345},
{"learn":[3.690900932],"iteration":618,"passed_time":0.5004255741,"remaining_time":0.3080163873},
{"learn":[3.688020895],"iteration":619,"passed_time":0.5009256562,"remaining_time":0.3070189506},
{"learn":[3.685491894],"iteration":620,"passed_time":0.5014925285,"remaining_time":0.3060638781},
{"learn":[3.684328128],"iteration":621,"passed_time":0.5019915,"remaining_time":0.3050687894},
{"learn":[3.680640153],"iteration":622,"passed_time":0.5024935473,"remaining_time":0.3040771546},
{"learn":[3.678932783],"iteration":623,"passed_time":0.5029790578,"remaining_time":0.3030771246},
{"learn":[3.674167041],"iteration":624,"passed_time":0.5034964264,"remaining_time":0.3020978559},
{"learn":[3.672200976],"iteration":625,"passed_time":0.5040625351,"remaining_time":0.3011491823},
{"learn":[3.670606604],"iteration":626,"passed_time":0.5047585669,"remaining_time":0.3002790199},
{"learn":[3.665506042],"iteration":627,"passed_time":0.505255933,"remaining_time":0.299291731},
{"learn":[3.664214007],"iteration":628,"passed_time":0.5057881089,"remaining_time":0.2983265317},
{"learn":[3.66261643],"iteration":629,"passed_time":0.5062786518,"remaining_time":0.2973382558},
{"learn":[3.662118449],"iteration":630,"passed_time":0.5067865975,"remaining_time":0.2963617345},
{"learn":[3.660871366],"iteration":631,"passed_time":0.5073046403,"remaining_time":0.2953925754},
{"learn":[3.656695243],"iteration":632,"passed_time":0.507806205,"remaining_time":0.2944152879},
{"learn":[3.654497801],"iteration":633,"passed_time":0.5083758278,"remaining_time":0.2934787902},
{"learn":[3.654189134],"iteration":634,"passed_time":0.5089278413,"remaining_time":0.2925333261},
{"learn":[3.653957699],"iteration":635,"passed_time":0.5095375592,"remaining_time":0.2916221251},
{"learn":[3.651920725],"iteration":636,"passed_time":0.5100641634,"remaining_time":0.2906645076},
{"learn":[3.65106705],"iteration":637,"passed_time":0.5105339335,"remaining_time":0.2896759936},
{"learn":[3.650612844],"iteration":638,"passed_time":0.5110187745,"remaining_time":0.2886976175},
{"learn":[3.649884732],"iteration":639,"passed_time":0.5115058056,"remaining_time":0.2877220156},
{"learn":[3.646276182],"iteration":640,"passed_time":0.5121045269,"remaining_time":0.2868104917},
{"learn":[3.645808194],"iteration":641,"passed_time":0.5126364652,"remaining_time":0.2858627018},
{"learn":[3.645042989],"iteration":642,"passed_time":0.5130946326,"remaining_time":0.284875247},
{"learn":[3.639864499],"iteration":643,"passed_time":0.513624232,"remaining_time":0.2839289233},
{"learn":[3.637318478],"iteration":644,"passed_time":0.5142062877,"remaining_time":0.283012763},
{"learn":[3.636344905],"iteration":645,"passed_time":0.5147772748,"remaining_time":0.2820915716},
{"learn":[3.634754643],"iteration":646,"passed_time":0.5152656709,"remaining_time":0.2811264016},
{"learn":[3.630724975],"iteration":647,"passed_time":0.5157232216,"remaining_time":0.2801459475},
{"learn":[3.629408252],"iteration":648,"passed_time":0.5161878098,"remaining_time":0.279170911},
{"learn":[3.62790646],"iteration":649,"passed_time":0.5166928555,"remaining_time":0.2782192299},
{"learn":[3.627388973],"iteration":650,"passed_time":0.5172202531,"remaining_time":0.2772809037},
{"learn":[3.625163557],"iteration":651,"passed_time":0.517709248,"remaining_time":0.276323341},
{"learn":[3.623701985],"iteration":652,"passed_time":0.5181860903,"remaining_time":0.2753607555},
{"learn":[3.622342639],"iteration":653,"passed_time":0.5186837214,"remaining_time":0.2744106538},
{"learn":[3.621130639],"iteration":654,"passed_time":0.5192173037,"remaining_time":0.2734808699},
{"learn":[3.619125665],"iteration":655,"passed_time":0.5197579757,"remaining_time":0.2725560116},
{"learn":[3.618878783],"iteration":656,"passed_time":0.5202527091,"remaining_time":0.2716083398},
{"learn":[3.616207429],"iteration":657,"passed_time":0.5207422133,"remaining_time":0.2706593267},
{"learn":[3.61206486],"iteration":658,"passed_time":0.5213360936,"remaining_time":0.2697657176},
{"learn":[3.611955873],"iteration":659,"passed_time":0.5218315773,"remaining_time":0.2688223277},
{"learn":[3.610713743],"iteration":660,"passed_time":0.5222991079,"remaining_time":0.267865957},
{"learn":[3.610044025],"iteration":661,"passed_time":0.5228136523,"remaining_time":0.2669350672},
{"learn":[3.607342669],"iteration":662,"passed_time":0.5232726487,"remaining_time":0.2659771985},
{"learn":[3.602510618],"iteration":663,"passed_time":0.523785479,"remaining_time":0.2650480737},
{"learn":[3.600492392],"iteration":664,"passed_time":0.5243553837,"remaining_time":0.2641489527},
{"learn":[3.597171065],"iteration":665,"passed_time":0.5248553264,"remaining_time":0.2632157343},
{"learn":[3.594358798],"iteration":666,"passed_time":0.5253716657,"remaining_time":0.262292001},
{"learn":[3.593945251],"iteration":667,"passed_time":0.525868668,"remaining_time":0.2613598769},
{"learn":[3.593607748],"iteration":668,"passed_time":0.5264026866,"remaining_time":0.2604473681},
{"learn":[3.592238714],"iteration":669,"passed_time":0.5268892337,"remaining_time":0.2595126077},
{"learn":[3.590144654],"iteration":670,"passed_time":0.5273979832,"remaining_time":0.2585900692},
{"learn":[3.587151536],"iteration":671,"passed_time":0.5278844135,"remaining_time":0.2576578685},
{"learn":[3.586070865],"iteration":672,"passed_time":0.5283390531,"remaining_time":0.2567115459},
{"learn":[3.585102746],"iteration":673,"passed_time":0.5289026059,"remaining_time":0.2558193613},
{"learn":[3.584362847],"iteration":674,"passed_time":0.5295182893,"remaining_time":0.2549532504},
{"learn":[3.581407561],"iteration":675,"passed_time":0.5300397904,"remaining_time":0.2540427398},
{"learn":[3.57919422],"iteration":676,"passed_time":0.5304942872,"remaining_time":0.2531014103},
{"learn":[3.577632204],"iteration":677,"passed_time":0.5310272868,"remaining_time":0.2521987999},
{"learn":[3.573911195],"iteration":678,"passed_time":0.5315074466,"remaining_time":0.251272298},
{"learn":[3.573408216],"iteration":679,"passed_time":0.5319394291,"remaining_time":0.2503244372},
{"learn":[3.571076482],"iteration":680,"passed_time":0.532399595,"remaining_time":0.2493912934},
{"learn":[3.568177107],"iteration":681,"passed_time":0.532884956,"remaining_time":0.2484712845},
{"learn":[3.564824621],"iteration":682,"passed_time":0.5334140861,"remaining_time":0.2475728628},
{"learn":[3.562475026],"iteration":683,"passed_time":0.5338785788,"remaining_time":0.2466456592},
{"learn":[3.561226889],"iteration":684,"passed_time":0.5344683566,"remaining_time":0.2457774195},
{"learn":[3.559383467],"iteration":685,"passed_time":0.5350165734,"remaining_time":0.244890968},
{"learn":[3.555209766],"iteration":686,"passed_time":0.5355275179,"remaining_time":0.2439885198},
{"learn":[3.55345383],"iteration":687,"passed_time":0.536012439,"remaining_time":0.2430754084},
{"learn":[3.552300968],"iteration":688,"passed_time":0.5365008231,"remaining_time":0.242165103},
{"learn":[3.551253986],"iteration":689,"passed_time":0.5369529736,"remaining_time":0.2412397418},
{"learn":[3.549807725],"iteration":690,"passed_time":0.5374638831,"remaining_time":0.2403420259},
{"learn":[3.547992926],"iteration":691,"passed_time":0.5379575325,"remaining_time":0.2394377457},
{"learn":[3.545438607],"iteration":692,"passed_time":0.5384161392,"remaining_time":0.2385191266},
{"learn":[3.543313763],"iteration":693,"passed_time":0.538919874,"remaining_time":0.2376217312},
{"learn":[3.542962896],"iteration":694,"passed_time":0.5394132137,"remaining_time":0.2367209067},
{"learn":[3.539800465],"iteration":695,"passed_time":0.539967203,"remaining_time":0.2358477439},
{"learn":[3.53953187],"iteration":696,"passed_time":0.540542845,"remaining_time":0.2349849097},
{"learn":[3.536332425],"iteration":697,"passed_time":0.5411594379,"remaining_time":0.2341406164},
{"learn":[3.534993327],"iteration":698,"passed_time":0.5417728547,"remaining_time":0.233295607},
{"learn":[3.531637011],"iteration":699,"passed_time":0.5423786173,"remaining_time":0.2324479788},
{"learn":[3.531040284],"iteration":700,"passed_time":0.542915427,"remaining_time":0.2315716301},
{"learn":[3.529973872],"iteration":701,"passed_time":0.543461931,"remaining_time":0.2307003639},
{"learn":[3.527325183],"iteration":702,"passed_time":0.5440154758,"remaining_time":0.2298329962},
{"learn":[3.527200815],"iteration":703,"passed_time":0.5446078071,"remaining_time":0.228982828},
{"learn":[3.523459911],"iteration":704,"passed_time":0.5451264901,"remaining_time":0.2281025739},
{"learn":[3.522729934],"iteration":705,"passed_time":0.5456615263,"remaining_time":0.227230154},
{"learn":[3.522260582],"iteration":706,"passed_time":0.5461689136,"remaining_time":0.2263472301},
{"learn":[3.518641591],"iteration":707,"passed_time":0.5466706229,"remaining_time":0.2254630253},
{"learn":[3.516856405],"iteration":708,"passed_time":0.5471547356,"remaining_time":0.2245726771},
{"learn":[3.515083413],"iteration":709,"passed_time":0.5476605564,"remaining_time":0.2236923399},
{"learn":[3.514671214],"iteration":710,"passed_time":0.5481341619,"remaining_time":0.2227999617},
{"learn":[3.512617621],"iteration":711,"passed_time":0.548600001,"remaining_time":0.2219056184},
{"learn":[3.510747971],"iteration":712,"passed_time":0.5491167942,"remaining_time":0.2210329873},
{"learn":[3.508149266],"iteration":713,"passed_time":0.5498159723,"remaining_time":0.2202344091},
{"learn":[3.504557165],"iteration":714,"passed_time":0.5503228771,"remaining_time":0.2193594685},
{"learn":[3.501367208],"iteration":715,"passed_time":0.5508146822,"remaining_time":0.2184795667},
{"learn":[3.497593362],"iteration":716,"passed_time":0.5513668847,"remaining_time":0.2176245863},
{"learn":[3.496291169],"iteration":717,"passed_time":0.5518329647,"remaining_time":0.216736624},
{"learn":[3.49330374],"iteration":718,"passed_time":0.5523151617,"remaining_time":0.2158561341},
{"learn":[3.490044385],"iteration":719,"passed_time":0.5528200213,"remaining_time":0.2149855638},
{"learn":[3.488891789],"iteration":720,"passed_time":0.5532898914,"remaining_time":0.2141024684},
{"learn":[3.486869081],"iteration":721,"passed_time":0.5537991321,"remaining_time":0.2132356769},
{"learn":[3.486303638],"iteration":722,"passed_time":0.5544638799,"remaining_time":0.2124294533},
{"learn":[3.486035862],"iteration":723,"passed_time":0.5549448381,"remaining_time":0.2115535571},
{"learn":[3.482668951],"iteration":724,"passed_time":0.5554580741,"remaining_time":0.2106909936},
{"learn":[3.47820549],"iteration":725,"passed_time":0.5559634837,"remaining_time":0.2098264388},
{"learn":[3.474392283],"iteration":726,"passed_time":0.556458071,"remaining_time":0.2089588079},
{"learn":[3.472268163],"iteration":727,"passed_time":0.5569135937,"remaining_time":0.2080776064},
{"learn":[3.471209164],"iteration":728,"passed_time":0.5573584985,"remaining_time":0.2071936256},
{"learn":[3.470049971],"iteration":729,"passed_time":0.5578572924,"remaining_time":0.2063307794},
{"learn":[3.469078654],"iteration":730,"passed_time":0.5583467492,"remaining_time":0.2054654932},
{"learn":[3.468643292],"iteration":731,"passed_time":0.5588257275,"remaining_time":0.2045973975},
{"learn":[3.468134848],"iteration":732,"passed_time":0.5593370438,"remaining_time":0.2037421428},
{"learn":[3.467820182],"iteration":733,"passed_time":0.5598581064,"remaining_time":0.2028913574},
{"learn":[3.465776156],"iteration":734,"passed_time":0.5603309002,"remaining_time":0.2020240661},
{"learn":[3.463037608],"iteration":735,"passed_time":0.5608106041,"remaining_time":0.2011603254},
{"learn":[3.45965637],"iteration":736,"passed_time":0.5612788302,"remaining_time":0.200293531},
{"learn":[3.457275091],"iteration":737,"passed_time":0.5617650856,"remaining_time":0.1994342174},
{"learn":[3.455522955],"iteration":738,"passed_time":0.5622325608,"remaining_time":0.1985692806},
{"learn":[3.451270508],"iteration":739,"passed_time":0.5628462526,"remaining_time":0.1977567915},
{"learn":[3.450978947],"iteration":740,"passed_time":0.5633037552,"remaining_time":0.1968902464},
{"learn":[3.450608492],"iteration":741,"passed_time":0.5637770143,"remaining_time":0.1960302826},
{"learn":[3.448122004],"iteration":742,"passed_time":0.5645308683,"remaining_time":0.1952684161},
{"learn":[3.445646714],"iteration":743,"passed_time":0.5651126053,"remaining_time":0.194447348},
{"learn":[3.44411263],"iteration":744,"passed_time":0.5656001116,"remaining_time":0.1935946691},
{"learn":[3.443264164],"iteration":745,"passed_time":0.5660446005,"remaining_time":0.1927283224},
{"learn":[3.439521363],"iteration":746,"passed_time":0.5665390262,"remaining_time":0.1918800182},
{"learn":[3.436809225],"iteration":747,"passed_time":0.5670357862,"remaining_time":0.1910334467},
{"learn":[3.435509465],"iteration":748,"passed_time":0.567567862,"remaining_time":0.190199644},
{"learn":[3.434450277],"iteration":749,"passed_time":0.5680415483,"remaining_time":0.1893471828},
{"learn":[3.431786753],"iteration":750,"passed_time":0.5685377656,"remaining_time":0.1885032006},
{"learn":[3.430150302],"iteration":751,"passed_time":0.5690952274,"remaining_time":0.1876803409},
{"learn":[3.42696281],"iteration":752,"passed_time":0.5697157161,"remaining_time":0.1868788604},
{"learn":[3.426870334],"iteration":753,"passed_time":0.5702100457,"remaining_time":0.1860366993},
{"learn":[3.425200309],"iteration":754,"passed_time":0.5707001601,"remaining_time":0.1851940917},
{"learn":[3.423383783],"iteration":755,"passed_time":0.5712012101,"remaining_time":0.1843559461},
{"learn":[3.422752979],"iteration":756,"passed_time":0.5716466188,"remaining_time":0.1835008301},
{"learn":[3.420845924],"iteration":757,"passed_time":0.572106447,"remaining_time":0.1826513986},
{"learn":[3.418917862],"iteration":758,"passed_time":0.5726507625,"remaining_time":0.1818298205},
{"learn":[3.417095735],"iteration":759,"passed_time":0.5731507393,"remaining_time":0.1809949703},
{"learn":[3.414391848],"iteration":760,"passed_time":0.5736199633,"remaining_time":0.1801513419},
{"learn":[3.41426711],"iteration":761,"passed_time":0.5740828913,"remaining_time":0.1793067298},
{"learn":[3.411976013],"iteration":762,"passed_time":0.574809737,"remaining_time":0.1785450952},
{"learn":[3.408614844],"iteration":763,"passed_time":0.5753061679,"remaining_time":0.1777123765},
{"learn":[3.407906721],"iteration":764,"passed_time":0.5757861241,"remaining_time":0.176875476},
{"learn":[3.407494015],"iteration":765,"passed_time":0.5763536799,"remaining_time":0.1760662677},
{"learn":[3.406287128],"iteration":766,"passed_time":0.5768670395,"remaining_time":0.1752412258},
{"learn":[3.404600442],"iteration":767,"passed_time":0.5773417938,"remaining_time":0.1744053335},
{"learn":[3.404012662],"iteration":768,"passed_time":0.5778293782,"remaining_time":0.1735742345},
{"learn":[3.400398762],"iteration":769,"passed_time":0.5783017315,"remaining_time":0.1727394782},
{"learn":[3.399737714],"iteration":770,"passed_time":0.5787818445,"remaining_time":0.1719079668},
{"learn":[3.399185251],"iteration":771,"passed_time":0.5792572423,"remaining_time":0.1710759731},
{"learn":[3.397245411],"iteration":772,"passed_time":0.5798703628,"remaining_time":0.1702853459},
{"learn":[3.396229831],"iteration":773,"passed_time":0.580365669,"remaining_time":0.1694607767},
{"learn":[3.394002836],"iteration":774,"passed_time":0.580852415,"remaining_time":0.1686345721},
{"learn":[3.389617243],"iteration":775,"passed_time":0.5813216444,"remaining_time":0.167804186},
{"learn":[3.385426488],"iteration":776,"passed_time":0.581814653,"remaining_time":0.1669815542},
{"learn":[3.385072258],"iteration":777,"passed_time":0.5822898832,"remaining_time":0.1661546968},
{"learn":[3.383842366],"iteration":778,"passed_time":0.5830117403,"remaining_time":0.1653987094},
{"learn":[3.380110746],"iteration":779,"passed_time":0.5836257926,"remaining_time":0.164612403},
{"learn":[3.378595218],"iteration":780,"passed_time":0.5841989738,"remaining_time":0.1638150772},
{"learn":[3.377371219],"iteration":781,"passed_time":0.5847868869,"remaining_time":0.1630224314},
{"learn":[3.375814782],"iteration":782,"passed_time":0.5853873962,"remaining_time":0.1622337994},
{"learn":[3.374195887],"iteration":783,"passed_time":0.5859869132,"remaining_time":0.161445374},
{"learn":[3.373704309],"iteration":784,"passed_time":0.5865283738,"remaining_time":0.1606415291},
{"learn":[3.372971757],"iteration":785,"passed_time":0.5870430363,"remaining_time":0.1598310557},
{"learn":[3.371565136],"iteration":786,"passed_time":0.5875693148,"remaining_time":0.1590244778},
{"learn":[3.3700309],"iteration":787,"passed_time":0.5880517722,"remaining_time":0.158206822},
{"learn":[3.368186663],"iteration":788,"passed_time":0.5885271426,"remaining_time":0.1573881205},
{"learn":[3.366710398],"iteration":789,"passed_time":0.5890346721,"remaining_time":0.1565788369},
{"learn":[3.364598042],"iteration":790,"passed_time":0.58954138,"remaining_time":0.1557700991},
{"learn":[3.36348442],"iteration":791,"passed_time":0.5901722829,"remaining_time":0.154994741},
{"learn":[3.362001759],"iteration":792,"passed_time":0.5906726387,"remaining_time":0.1541856699},
{"learn":[3.361580401],"iteration":793,"passed_time":0.5911656413,"remaining_time":0.1533754687},
{"learn":[3.359543675],"iteration":794,"passed_time":0.5916350676,"remaining_time":0.152559986},
{"learn":[3.35766119],"iteration":795,"passed_time":0.5920973075,"remaining_time":0.1517435311},
{"learn":[3.354592969],"iteration":796,"passed_time":0.5925781822,"remaining_time":0.1509327114},
{"learn":[3.350985986],"iteration":797,"passed_time":0.5930523631,"remaining_time":0.1501210242},
{"learn":[3.349589624],"iteration":798,"passed_time":0.5935422404,"remaining_time":0.1493141306},
{"learn":[3.349110856],"iteration":799,"passed_time":0.5940281221,"remaining_time":0.1485070305},
{"learn":[3.345315441],"iteration":800,"passed_time":0.5945223135,"remaining_time":0.147702797},
{"learn":[3.34397474],"iteration":801,"passed_time":0.595107083,"remaining_time":0.1469216988},
{"learn":[3.343800902],"iteration":802,"passed_time":0.5955606039,"remaining_time":0.1461088904},
{"learn":[3.342329465],"iteration":803,"passed_time":0.596032861,"remaining_time":0.1453015432},
{"learn":[3.34220347],"iteration":804,"passed_time":0.5965093579,"remaining_time":0.1444960556},
{"learn":[3.341279219],"iteration":805,"passed_time":0.5970351444,"remaining_time":0.1437032482},
{"learn":[3.337329521],"iteration":806,"passed_time":0.5976614141,"remaining_time":0.1429351337},
{"learn":[3.336708453],"iteration":807,"passed_time":0.5982086894,"remaining_time":0.1421485995},
{"learn":[3.333252703],"iteration":808,"passed_time":0.5987434015,"remaining_time":0.1413596906},
{"learn":[3.332186769],"iteration":809,"passed_time":0.5992942626,"remaining_time":0.1405751974},
{"learn":[3.330594851],"iteration":810,"passed_time":0.5999505204,"remaining_time":0.1398158426},
{"learn":[3.327867442],"iteration":811,"passed_time":0.6004468725,"remaining_time":0.1390197193},
{"learn":[3.327563111],"iteration":812,"passed_time":0.6009525451,"remaining_time":0.1382264772},
{"learn":[3.326308994],"iteration":813,"passed_time":0.6014753332,"remaining_time":0.1374378525},
{"learn":[3.326249879],"iteration":814,"passed_time":0.60194995,"remaining_time":0.1366389457},
{"learn":[3.322336238],"iteration":815,"passed_time":0.60245943,"remaining_time":0.135848695},
{"learn":[3.320491154],"iteration":816,"passed_time":0.6029465359,"remaining_time":0.13505412},
{"learn":[3.320434271],"iteration":817,"passed_time":0.6034500684,"remaining_time":0.1342639516},
{"learn":[3.319609638],"iteration":818,"passed_time":0.6039153488,"remaining_time":0.1334660295},
{"learn":[3.316182682],"iteration":819,"passed_time":0.6045064846,"remaining_time":0.1326965454},
{"learn":[3.313126612],"iteration":820,"passed_time":0.6050811036,"remaining_time":0.1319238947},
{"learn":[3.311222803],"iteration":821,"passed_time":0.6056129765,"remaining_time":0.1311424694},
{"learn":[3.309627335],"iteration":822,"passed_time":0.6061052875,"remaining_time":0.130353142},
{"learn":[3.307974895],"iteration":823,"passed_time":0.6065945134,"remaining_time":0.1295638766},
{"learn":[3.307321505],"iteration":824,"passed_time":0.6071016798,"remaining_time":0.1287791442},
{"learn":[3.306759087],"iteration":825,"passed_time":0.6075748642,"remaining_time":0.1279879254},
{"learn":[3.30484037],"iteration":826,"passed_time":0.6080790208,"remaining_time":0.1272039548},
{"learn":[3.30201994],"iteration":827,"passed_time":0.6085935839,"remaining_time":0.1264228218},
{"learn":[3.299302297],"iteration":828,"passed_time":0.6090945799,"remaining_time":0.1256395334},
{"learn":[3.298132671],"iteration":829,"passed_time":0.6096133106,"remaining_time":0.1248605576},
{"learn":[3.296976183],"iteration":830,"passed_time":0.6103156674,"remaining_time":0.1241195521},
{"learn":[3.293144745],"iteration":831,"passed_time":0.6107958138,"remaining_time":0.1233337701},
{"learn":[3.290284404],"iteration":832,"passed_time":0.6112551988,"remaining_time":0.1225445597},
{"learn":[3.288285745],"iteration":833,"passed_time":0.6118435477,"remaining_time":0.1217818093},
{"learn":[3.286662667],"iteration":834,"passed_time":0.6123782769,"remaining_time":0.1210088811},
{"learn":[3.285692682],"iteration":835,"passed_time":0.6128981546,"remaining_time":0.1202336093},
{"learn":[3.284565611],"iteration":836,"passed_time":0.6134126563,"remaining_time":0.1194579008},
{"learn":[3.283897383],"iteration":837,"passed_time":0.6139138546,"remaining_time":0.118680244},
{"learn":[3.280712855],"iteration":838,"passed_time":0.6144162643,"remaining_time":0.1179034786},
{"learn":[3.280468341],"iteration":839,"passed_time":0.6150016079,"remaining_time":0.1171431634},
{"learn":[3.277814895],"iteration":840,"passed_time":0.6155352536,"remaining_time":0.1163734903},
{"learn":[3.276316385],"iteration":841,"passed_time":0.616055379,"remaining_time":0.1156018407},
{"learn":[3.27557063],"iteration":842,"passed_time":0.6165562509,"remaining_time":0.1148272021},
{"learn":[3.27499628],"iteration":843,"passed_time":0.6170407528,"remaining_time":0.1140501865},
{"learn":[3.273569958],"iteration":844,"passed_time":0.6175619816,"remaining_time":0.1132806002},
{"learn":[3.269665595],"iteration":845,"passed_time":0.6180358301,"remaining_time":0.1125029762},
{"learn":[3.267984685],"iteration":846,"passed_time":0.6184981321,"remaining_time":0.1117239837},
{"learn":[3.267702508],"iteration":847,"passed_time":0.6189757113,"remaining_time":0.1109484765},
{"learn":[3.266671924],"iteration":848,"passed_time":0.6194417152,"remaining_time":0.1101716125},
{"learn":[3.265359825],"iteration":849,"passed_time":0.620006091,"remaining_time":0.1094128396},
{"learn":[3.2618983],"iteration":850,"passed_time":0.6205570038,"remaining_time":0.1086521664},
{"learn":[3.260456253],"iteration":851,"passed_time":0.6210352098,"remaining_time":0.1078793557},
{"learn":[3.258389147],"iteration":852,"passed_time":0.6215398811,"remaining_time":0.1071117966},
{"learn":[3.258108469],"iteration":853,"passed_time":0.6219986626,"remaining_time":0.1063370079},
{"learn":[3.256424936],"iteration":854,"passed_time":0.6224895413,"remaining_time":0.1055684017},
{"learn":[3.254817983],"iteration":855,"passed_time":0.622966005,"remaining_time":0.1047980195},
{"learn":[3.253898449],"iteration":856,"passed_time":0.6234503034,"remaining_time":0.1040296305},
{"learn":[3.253023652],"iteration":857,"passed_time":0.623903877,"remaining_time":0.1032568188},
{"learn":[3.252845542],"iteration":858,"passed_time":0.6243860813,"remaining_time":0.1024894499},
{"learn":[3.252316026],"iteration":859,"passed_time":0.6249979733,"remaining_time":0.1017438561},
{"learn":[3.24975301],"iteration":860,"passed_time":0.6255368443,"remaining_time":0.1009867844},
{"learn":[3.249151075],"iteration":861,"passed_time":0.6260074871,"remaining_time":0.1002192961},
{"learn":[3.246257135],"iteration":862,"passed_time":0.6265895188,"remaining_time":0.09947017853},
{"learn":[3.243826471],"iteration":863,"passed_time":0.6270876799,"remaining_time":0.09870824591},
{"learn":[3.243190653],"iteration":864,"passed_time":0.6275915001,"remaining_time":0.09794780637},
{"learn":[3.24008797],"iteration":865,"passed_time":0.628051138,"remaining_time":0.09718112298},
{"learn":[3.240036811],"iteration":866,"passed_time":0.6285147517,"remaining_time":0.09641575775},
{"learn":[3.238676314],"iteration":867,"passed_time":0.6289724245,"remaining_time":0.09565018436},
{"learn":[3.237848782],"iteration":868,"passed_time":0.6294302521,"remaining_time":0.09488534295},
{"learn":[3.236405498],"iteration":869,"passed_time":0.6300573265,"remaining_time":0.09414649706},
{"learn":[3.233378068],"iteration":870,"passed_time":0.6306319989,"remaining_time":0.0934001468},
{"learn":[3.233169169],"iteration":871,"passed_time":0.6310914927,"remaining_time":0.09263728333},
{"learn":[3.232434885],"iteration":872,"passed_time":0.6315629261,"remaining_time":0.0918768518},
{"learn":[3.229978115],"iteration":873,"passed_time":0.6320719489,"remaining_time":0.09112250064},
{"learn":[3.229648848],"iteration":874,"passed_time":0.6325262728,"remaining_time":0.09036089612},
{"learn":[3.227208761],"iteration":875,"passed_time":0.6329986228,"remaining_time":0.08960254478},
{"learn":[3.226258869],"iteration":876,"passed_time":0.6335266548,"remaining_time":0.08885265512},
{"learn":[3.225331995],"iteration":877,"passed_time":0.6340694411,"remaining_time":0.08810532097},
{"learn":[3.221968268],"iteration":878,"passed_time":0.6345771355,"remaining_time":0.08735362161},
{"learn":[3.221166317],"iteration":879,"passed_time":0.6352373623,"remaining_time":0.08662327668},
{"learn":[3.220047503],"iteration":880,"passed_time":0.6357511457,"remaining_time":0.08587331026},
{"learn":[3.21982781],"iteration":881,"passed_time":0.636219773,"remaining_time":0.08511783811},
{"learn":[3.216693405],"iteration":882,"passed_time":0.6366922304,"remaining_time":0.08436352317},
{"learn":[3.214798761],"iteration":883,"passed_time":0.6371810694,"remaining_time":0.08361199554},
{"learn":[3.214395085],"iteration":884,"passed_time":0.6376455054,"remaining_time":0.08285789053},
{"learn":[3.213470696],"iteration":885,"passed_time":0.6381277865,"remaining_time":0.08210673551},
{"learn":[3.211595017],"iteration":886,"passed_time":0.6386483805,"remaining_time":0.08136106764},
{"learn":[3.210965255],"iteration":887,"passed_time":0.6391493034,"remaining_time":0.08061342566},
{"learn":[3.209413583],"iteration":888,"passed_time":0.6396641068,"remaining_time":0.07986807183},
{"learn":[3.208331683],"iteration":889,"passed_time":0.6403555082,"remaining_time":0.07914506281},
{"learn":[3.207110711],"iteration":890,"passed_time":0.6410180262,"remaining_time":0.07841859131},
{"learn":[3.204519413],"iteration":891,"passed_time":0.6417129146,"remaining_time":0.07769618249},
{"learn":[3.201421296],"iteration":892,"passed_time":0.6422794521,"remaining_time":0.07695845619},
{"learn":[3.200691259],"iteration":893,"passed_time":0.642907959,"remaining_time":0.07622846046},
{"learn":[3.200485067],"iteration":894,"passed_time":0.6436837242,"remaining_time":0.07551596764},
{"learn":[3.197467568],"iteration":895,"passed_time":0.6443060146,"remaining_time":0.07478551955},
{"learn":[3.195838544],"iteration":896,"passed_time":0.6448591986,"remaining_time":0.07404737732},
{"learn":[3.195671746],"iteration":897,"passed_time":0.6455496197,"remaining_time":0.0733252352},
{"learn":[3.194213094],"iteration":898,"passed_time":0.6460722336,"remaining_time":0.072584311},
{"learn":[3.192884691],"iteration":899,"passed_time":0.6465577528,"remaining_time":0.07183975031},
{"learn":[3.188364239],"iteration":900,"passed_time":0.6470284179,"remaining_time":0.07109413249},
{"learn":[3.185219478],"iteration":901,"passed_time":0.6475232215,"remaining_time":0.0703517469},
{"learn":[3.184120387],"iteration":902,"passed_time":0.6480132447,"remaining_time":0.06960939616},
{"learn":[3.183725321],"iteration":903,"passed_time":0.6485402918,"remaining_time":0.06887153541},
{"learn":[3.181264554],"iteration":904,"passed_time":0.6490693832,"remaining_time":0.06813435514},
{"learn":[3.180741589],"iteration":905,"passed_time":0.6495400937,"remaining_time":0.06739157705},
{"learn":[3.179782639],"iteration":906,"passed_time":0.6500017522,"remaining_time":0.06664847073},
{"learn":[3.176377564],"iteration":907,"passed_time":0.6505456869,"remaining_time":0.0659143207},
{"learn":[3.174078182],"iteration":908,"passed_time":0.651034007,"remaining_time":0.0651750216},
{"learn":[3.171242379],"iteration":909,"passed_time":0.6515128911,"remaining_time":0.06443534088},
{"learn":[3.170421012],"iteration":910,"passed_time":0.6519992554,"remaining_time":0.06369696348},
{"learn":[3.170087224],"iteration":911,"passed_time":0.6524703791,"remaining_time":0.06295766816},
{"learn":[3.167303059],"iteration":912,"passed_time":0.6529792851,"remaining_time":0.06222256057},
{"learn":[3.16705966],"iteration":913,"passed_time":0.6535315319,"remaining_time":0.06149202598},
{"learn":[3.165667683],"iteration":914,"passed_time":0.6540714042,"remaining_time":0.06076073154},
{"learn":[3.164689733],"iteration":915,"passed_time":0.6545499553,"remaining_time":0.06002423171},
{"learn":[3.163311455],"iteration":916,"passed_time":0.6550636379,"remaining_time":0.05929147432},
{"learn":[3.159425016],"iteration":917,"passed_time":0.655539523,"remaining_time":0.05855581796},
{"learn":[3.159327058],"iteration":918,"passed_time":0.6559717631,"remaining_time":0.0578168801},
{"learn":[3.15819426],"iteration":919,"passed_time":0.6564363693,"remaining_time":0.05708142342},
{"learn":[3.157086603],"iteration":920,"passed_time":0.6569092813,"remaining_time":0.05634726734},
{"learn":[3.153354154],"iteration":921,"passed_time":0.6574277299,"remaining_time":0.0556175303},
{"learn":[3.153261317],"iteration":922,"passed_time":0.6578875982,"remaining_time":0.05488336409},
{"learn":[3.153168454],"iteration":923,"passed_time":0.6584200464,"remaining_time":0.0541557614},
{"learn":[3.152080399],"iteration":924,"passed_time":0.6589837057,"remaining_time":0.05343111127},
{"learn":[3.151635144],"iteration":925,"passed_time":0.6594923439,"remaining_time":0.05270241194},
{"learn":[3.147762655],"iteration":926,"passed_time":0.6599628315,"remaining_time":0.05197118307},
{"learn":[3.147172317],"iteration":927,"passed_time":0.660438272,"remaining_time":0.05124090042},
{"learn":[3.146254125],"iteration":928,"passed_time":0.6609284344,"remaining_time":0.05051229154},
{"learn":[3.144869828],"iteration":929,"passed_time":0.6614231045,"remaining_time":0.04978453474},
{"learn":[3.143466218],"iteration":930,"passed_time":0.6618947148,"remaining_time":0.04905556963},
{"learn":[3.141919643],"iteration":931,"passed_time":0.6624404218,"remaining_time":0.04833256296},
{"learn":[3.141054135],"iteration":932,"passed_time":0.6629409638,"remaining_time":0.04760669301},
{"learn":[3.139390417],"iteration":933,"passed_time":0.6634803251,"remaining_time":0.04688404867},
{"learn":[3.139025283],"iteration":934,"passed_time":0.6639804427,"remaining_time":0.04615906821},
{"learn":[3.137824183],"iteration":935,"passed_time":0.6645018945,"remaining_time":0.04543602697},
{"learn":[3.135620453],"iteration":936,"passed_time":0.6650425471,"remaining_time":0.04471470701},
{"learn":[3.13443178],"iteration":937,"passed_time":0.6655662136,"remaining_time":0.04399264951},
{"learn":[3.132765713],"iteration":938,"passed_time":0.6660867095,"remaining_time":0.0432708086},
{"learn":[3.131434124],"iteration":939,"passed_time":0.6665374963,"remaining_time":0.04254494657},
{"learn":[3.128384262],"iteration":940,"passed_time":0.667126464,"remaining_time":0.04182833303},
{"learn":[3.128120455],"iteration":941,"passed_time":0.6676229911,"remaining_time":0.04110629881},
{"learn":[3.126314615],"iteration":942,"passed_time":0.6681063749,"remaining_time":0.04038394843},
{"learn":[3.125409666],"iteration":943,"passed_time":0.6687849768,"remaining_time":0.03967368507},
{"learn":[3.123072589],"iteration":944,"passed_time":0.6693288074,"remaining_time":0.03895564488},
{"learn":[3.122921099],"iteration":945,"passed_time":0.6698790881,"remaining_time":0.03823834118},
{"learn":[3.122182662],"iteration":946,"passed_time":0.6704309118,"remaining_time":0.03752147658},
{"learn":[3.120040951],"iteration":947,"passed_time":0.6709686494,"remaining_time":0.03680418752},
{"learn":[3.118767799],"iteration":948,"passed_time":0.6714947313,"remaining_time":0.03608665047},
{"learn":[3.118203218],"iteration":949,"passed_time":0.6720237245,"remaining_time":0.03536966971},
{"learn":[3.116343362],"iteration":950,"passed_time":0.6726420676,"remaining_time":0.03465768803},
{"learn":[3.11480829],"iteration":951,"passed_time":0.6731207495,"remaining_time":0.03393886132},
{"learn":[3.112607903],"iteration":952,"passed_time":0.6737614147,"remaining_time":0.03322852727},
{"learn":[3.111661241],"iteration":953,"passed_time":0.674299751,"remaining_time":0.03251340518},
{"learn":[3.110249676],"iteration":954,"passed_time":0.6748207428,"remaining_time":0.03179783605},
{"learn":[3.107333579],"iteration":955,"passed_time":0.6752810817,"remaining_time":0.03107988242},
{"learn":[3.107149851],"iteration":956,"passed_time":0.6757663839,"remaining_time":0.03036358883},
{"learn":[3.106867336],"iteration":957,"passed_time":0.6762393206,"remaining_time":0.02964723535},
{"learn":[3.10364681],"iteration":958,"passed_time":0.6767151276,"remaining_time":0.02893151223},
{"learn":[3.102703811],"iteration":959,"passed_time":0.6771903731,"remaining_time":0.02821626555},
{"learn":[3.101469264],"iteration":960,"passed_time":0.6777415827,"remaining_time":0.02750460117},
{"learn":[3.09863569],"iteration":961,"passed_time":0.678248082,"remaining_time":0.02679150428},
{"learn":[3.09645939],"iteration":962,"passed_time":0.6788967756,"remaining_time":0.02608429979},
{"learn":[3.096240186],"iteration":963,"passed_time":0.6793493553,"remaining_time":0.02536989294},
{"learn":[3.094838828],"iteration":964,"passed_time":0.6798245862,"remaining_time":0.02465685028},
{"learn":[3.094176802],"iteration":965,"passed_time":0.680288621,"remaining_time":0.02394390591},
{"learn":[3.093182279],"iteration":966,"passed_time":0.6807725769,"remaining_time":0.02323215619},
{"learn":[3.090150687],"iteration":967,"passed_time":0.6812823703,"remaining_time":0.02252173125},
{"learn":[3.088612829],"iteration":968,"passed_time":0.681936742,"remaining_time":0.02181634572},
{"learn":[3.087153684],"iteration":969,"passed_time":0.6824905308,"remaining_time":0.02110795456},
{"learn":[3.085866843],"iteration":970,"passed_time":0.6830790153,"remaining_time":0.02040091807},
{"learn":[3.082669094],"iteration":971,"passed_time":0.6836614945,"remaining_time":0.01969395252},
{"learn":[3.081047548],"iteration":972,"passed_time":0.6843916293,"remaining_time":0.01899134018},
{"learn":[3.079684322],"iteration":973,"passed_time":0.6851034801,"remaining_time":0.01828818325},
{"learn":[3.07613431],"iteration":974,"passed_time":0.6856174972,"remaining_time":0.01757993582},
{"learn":[3.074005935],"iteration":975,"passed_time":0.686183219,"remaining_time":0.01687335784},
{"learn":[3.072988853],"iteration":976,"passed_time":0.6866810143,"remaining_time":0.01616546912},
{"learn":[3.072344268],"iteration":977,"passed_time":0.6872442269,"remaining_time":0.01545948159},
{"learn":[3.070654438],"iteration":978,"passed_time":0.6877788313,"remaining_time":0.01475317207},
{"learn":[3.069724506],"iteration":979,"passed_time":0.6882921177,"remaining_time":0.01404677791},
{"learn":[3.067763166],"iteration":980,"passed_time":0.6889109124,"remaining_time":0.01334282093},
{"learn":[3.066737893],"iteration":981,"passed_time":0.6895022644,"remaining_time":0.01263853438},
{"learn":[3.065248174],"iteration":982,"passed_time":0.6899893696,"remaining_time":0.01193267475},
{"learn":[3.063186837],"iteration":983,"passed_time":0.6904690488,"remaining_time":0.011227139},
{"learn":[3.062880371],"iteration":984,"passed_time":0.6909237999,"remaining_time":0.01052168223},
{"learn":[3.061288645],"iteration":985,"passed_time":0.6914392768,"remaining_time":0.009817596222},
{"learn":[3.059970575],"iteration":986,"passed_time":0.6919600177,"remaining_time":0.009113961732},
{"learn":[3.059576341],"iteration":987,"passed_time":0.6924789296,"remaining_time":0.008410675258},
{"learn":[3.058175919],"iteration":988,"passed_time":0.6929742698,"remaining_time":0.007707499462},
{"learn":[3.056830702],"iteration":989,"passed_time":0.693522072,"remaining_time":0.007005273455},
{"learn":[3.056336579],"iteration":990,"passed_time":0.694027525,"remaining_time":0.006302974495},
{"learn":[3.055810414],"iteration":991,"passed_time":0.6945350238,"remaining_time":0.005601088902},
{"learn":[3.055476518],"iteration":992,"passed_time":0.6951632296,"remaining_time":0.004900445728},
{"learn":[3.053331734],"iteration":993,"passed_time":0.6956537718,"remaining_time":0.004199117335},
{"learn":[3.050890374],"iteration":994,"passed_time":0.6961280462,"remaining_time":0.003498130885},
{"learn":[3.04972623],"iteration":995,"passed_time":0.6966661169,"remaining_time":0.002797855891},
{"learn":[3.047217327],"iteration":996,"passed_time":0.6971832699,"remaining_time":0.00209784334},
{"learn":[3.047155483],"iteration":997,"passed_time":0.6976888557,"remaining_time":0.001398174059},
{"learn":[3.04430671],"iteration":998,"passed_time":0.6981491271,"remaining_time":0.000698847975},
{"learn":[3.042664195],"iteration":999,"passed_time":0.6987270152,"remaining_time":0}
]}